{"box_data": [{"position": {"minX": 300.5807800292969, "minY": 76.73179626464844, "maxX": 431.9192199707031, "maxY": 92.39320373535156}, "class_id": 0, "box_caption": "RiceSpike 0.790", "scores": {"class_score": 0.7900390625}, "domain": "pixel"}, {"position": {"minX": 754.698486328125, "minY": 171.96749877929688, "maxX": 828.301513671875, "maxY": 200.78250122070312}, "class_id": 0, "box_caption": "RiceSpike 0.752", "scores": {"class_score": 0.75244140625}, "domain": "pixel"}, {"position": {"minX": 844.993896484375, "minY": 222.4620819091797, "maxX": 867.006103515625, "maxY": 234.7879180908203}, "class_id": 0, "box_caption": "RiceSpike 0.699", "scores": {"class_score": 0.69873046875}, "domain": "pixel"}, {"position": {"minX": 755.9163818359375, "minY": 158.4139862060547, "maxX": 825.0836181640625, "maxY": 214.0860137939453}, "class_id": 0, "box_caption": "RiceSpike 0.695", "scores": {"class_score": 0.69482421875}, "domain": "pixel"}, {"position": {"minX": 128.50869750976562, "minY": 219.14344787597656, "maxX": 199.74130249023438, "maxY": 236.10655212402344}, "class_id": 0, "box_caption": "RiceSpike 0.694", "scores": {"class_score": 0.69384765625}, "domain": "pixel"}, {"position": {"minX": 881.14306640625, "minY": 241.52798461914062, "maxX": 905.85693359375, "maxY": 294.9720153808594}, "class_id": 0, "box_caption": "RiceSpike 0.694", "scores": {"class_score": 0.69384765625}, "domain": "pixel"}, {"position": {"minX": 635.5361328125, "minY": 406.9458923339844, "maxX": 691.4638671875, "maxY": 453.0541076660156}, "class_id": 0, "box_caption": "RiceSpike 0.689", "scores": {"class_score": 0.689453125}, "domain": "pixel"}, {"position": {"minX": 369.43408203125, "minY": 211.99424743652344, "maxX": 439.56591796875, "maxY": 223.00575256347656}, "class_id": 0, "box_caption": "RiceSpike 0.684", "scores": {"class_score": 0.68359375}, "domain": "pixel"}, {"position": {"minX": 546.2076416015625, "minY": 465.1485595703125, "maxX": 600.7923583984375, "maxY": 597.8514404296875}, "class_id": 0, "box_caption": "RiceSpike 0.661", "scores": {"class_score": 0.6611328125}, "domain": "pixel"}, {"position": {"minX": 530.20263671875, "minY": 124.48081970214844, "maxX": 624.79736328125, "maxY": 142.01918029785156}, "class_id": 0, "box_caption": "RiceSpike 0.644", "scores": {"class_score": 0.6435546875}, "domain": "pixel"}, {"position": {"minX": 277.55584716796875, "minY": 401.93621826171875, "maxX": 348.94415283203125, "maxY": 417.56378173828125}, "class_id": 0, "box_caption": "RiceSpike 0.640", "scores": {"class_score": 0.64013671875}, "domain": "pixel"}, {"position": {"minX": 836.013671875, "minY": 484.1021728515625, "maxX": 892.986328125, "maxY": 527.3978271484375}, "class_id": 0, "box_caption": "RiceSpike 0.614", "scores": {"class_score": 0.6142578125}, "domain": "pixel"}, {"position": {"minX": 128.45126342773438, "minY": 105.5577392578125, "maxX": 250.29873657226562, "maxY": 125.0672607421875}, "class_id": 0, "box_caption": "RiceSpike 0.611", "scores": {"class_score": 0.61083984375}, "domain": "pixel"}, {"position": {"minX": 1008.47802734375, "minY": 88.78810119628906, "maxX": 1041.52197265625, "maxY": 113.21189880371094}, "class_id": 0, "box_caption": "RiceSpike 0.607", "scores": {"class_score": 0.607421875}, "domain": "pixel"}, {"position": {"minX": 837.4420776367188, "minY": 255.92642211914062, "maxX": 853.5579223632812, "maxY": 305.0735778808594}, "class_id": 0, "box_caption": "RiceSpike 0.600", "scores": {"class_score": 0.599609375}, "domain": "pixel"}, {"position": {"minX": 867.027587890625, "minY": 410.46844482421875, "maxX": 888.972412109375, "maxY": 466.03155517578125}, "class_id": 0, "box_caption": "RiceSpike 0.594", "scores": {"class_score": 0.59423828125}, "domain": "pixel"}, {"position": {"minX": 634.94384765625, "minY": 418.9626770019531, "maxX": 695.05615234375, "maxY": 440.0373229980469}, "class_id": 0, "box_caption": "RiceSpike 0.592", "scores": {"class_score": 0.591796875}, "domain": "pixel"}, {"position": {"minX": 520.1565551757812, "minY": 268.5420837402344, "maxX": 642.8434448242188, "maxY": 336.4579162597656}, "class_id": 0, "box_caption": "RiceSpike 0.590", "scores": {"class_score": 0.59033203125}, "domain": "pixel"}, {"position": {"minX": 604.8413696289062, "minY": 72.04662322998047, "maxX": 639.1586303710938, "maxY": 82.82837677001953}, "class_id": 0, "box_caption": "RiceSpike 0.569", "scores": {"class_score": 0.5693359375}, "domain": "pixel"}, {"position": {"minX": 238.91506958007812, "minY": 448.23553466796875, "maxX": 421.5849304199219, "maxY": 560.2644653320312}, "class_id": 0, "box_caption": "RiceSpike 0.569", "scores": {"class_score": 0.56884765625}, "domain": "pixel"}, {"position": {"minX": 183.25759887695312, "minY": 375.6281433105469, "maxX": 272.4924011230469, "maxY": 443.8718566894531}, "class_id": 0, "box_caption": "RiceSpike 0.566", "scores": {"class_score": 0.56640625}, "domain": "pixel"}, {"position": {"minX": 57.148101806640625, "minY": 43.65509796142578, "maxX": 146.22689819335938, "maxY": 57.65740203857422}, "class_id": 0, "box_caption": "RiceSpike 0.565", "scores": {"class_score": 0.5654296875}, "domain": "pixel"}, {"position": {"minX": 172.47152709960938, "minY": 388.73046875, "maxX": 281.7784729003906, "maxY": 430.26953125}, "class_id": 0, "box_caption": "RiceSpike 0.564", "scores": {"class_score": 0.564453125}, "domain": "pixel"}, {"position": {"minX": 388.62298583984375, "minY": 449.5517883300781, "maxX": 550.3770141601562, "maxY": 478.9482116699219}, "class_id": 0, "box_caption": "RiceSpike 0.561", "scores": {"class_score": 0.56103515625}, "domain": "pixel"}, {"position": {"minX": 389.4942626953125, "minY": 432.47344970703125, "maxX": 550.5057373046875, "maxY": 494.02655029296875}, "class_id": 0, "box_caption": "RiceSpike 0.561", "scores": {"class_score": 0.560546875}, "domain": "pixel"}, {"position": {"minX": 542.5879516601562, "minY": 475.32183837890625, "maxX": 596.4120483398438, "maxY": 589.6781616210938}, "class_id": 0, "box_caption": "RiceSpike 0.558", "scores": {"class_score": 0.55810546875}, "domain": "pixel"}, {"position": {"minX": 501.461669921875, "minY": 387.178955078125, "maxX": 625.538330078125, "maxY": 501.821044921875}, "class_id": 0, "box_caption": "RiceSpike 0.557", "scores": {"class_score": 0.55712890625}, "domain": "pixel"}, {"position": {"minX": 492.68780517578125, "minY": 399.6361389160156, "maxX": 630.3121948242188, "maxY": 492.8638610839844}, "class_id": 0, "box_caption": "RiceSpike 0.556", "scores": {"class_score": 0.5556640625}, "domain": "pixel"}, {"position": {"minX": 482.9375, "minY": 437.015625, "maxX": 639.0625, "maxY": 455.984375}, "class_id": 0, "box_caption": "RiceSpike 0.548", "scores": {"class_score": 0.5478515625}, "domain": "pixel"}, {"position": {"minX": 819.6123046875, "minY": 115.2773666381836, "maxX": 843.3876953125, "maxY": 125.2226333618164}, "class_id": 0, "box_caption": "RiceSpike 0.543", "scores": {"class_score": 0.54345703125}, "domain": "pixel"}, {"position": {"minX": 175.78976440429688, "minY": 401.78729248046875, "maxX": 280.4602355957031, "maxY": 415.71270751953125}, "class_id": 0, "box_caption": "RiceSpike 0.543", "scores": {"class_score": 0.54296875}, "domain": "pixel"}, {"position": {"minX": 88.56454467773438, "minY": 418.92901611328125, "maxX": 154.18545532226562, "maxY": 427.57098388671875}, "class_id": 0, "box_caption": "RiceSpike 0.539", "scores": {"class_score": 0.53857421875}, "domain": "pixel"}, {"position": {"minX": 240.74334716796875, "minY": 513.8328247070312, "maxX": 283.25665283203125, "maxY": 566.1671752929688}, "class_id": 0, "box_caption": "RiceSpike 0.526", "scores": {"class_score": 0.52587890625}, "domain": "pixel"}, {"position": {"minX": 270.7171936035156, "minY": 256.74407958984375, "maxX": 371.2828063964844, "maxY": 333.25592041015625}, "class_id": 0, "box_caption": "RiceSpike 0.517", "scores": {"class_score": 0.51708984375}, "domain": "pixel"}, {"position": {"minX": 230.42138671875, "minY": 481.0225830078125, "maxX": 426.07861328125, "maxY": 525.4774169921875}, "class_id": 0, "box_caption": "RiceSpike 0.517", "scores": {"class_score": 0.51708984375}, "domain": "pixel"}, {"position": {"minX": 261.0260314941406, "minY": 275.8113708496094, "maxX": 381.4739685058594, "maxY": 315.6886291503906}, "class_id": 0, "box_caption": "RiceSpike 0.512", "scores": {"class_score": 0.51171875}, "domain": "pixel"}, {"position": {"minX": 869.8203125, "minY": 75.283203125, "maxX": 894.1796875, "maxY": 81.966796875}, "class_id": 0, "box_caption": "RiceSpike 0.511", "scores": {"class_score": 0.5107421875}, "domain": "pixel"}, {"position": {"minX": 266.2035217285156, "minY": 283.9738464355469, "maxX": 374.7964782714844, "maxY": 307.5261535644531}, "class_id": 0, "box_caption": "RiceSpike 0.506", "scores": {"class_score": 0.505859375}, "domain": "pixel"}, {"position": {"minX": 522.84375, "minY": 401.46875, "maxX": 641.15625, "maxY": 419.03125}, "class_id": 0, "box_caption": "RiceSpike 0.501", "scores": {"class_score": 0.50146484375}, "domain": "pixel"}, {"position": {"minX": 1016.486328125, "minY": 78.27629089355469, "maxX": 1030.513671875, "maxY": 91.22370910644531}, "class_id": 0, "box_caption": "RiceSpike 0.499", "scores": {"class_score": 0.4990234375}, "domain": "pixel"}, {"position": {"minX": 17.696582794189453, "minY": 67.01192474365234, "maxX": 133.42840576171875, "maxY": 79.73807525634766}, "class_id": 0, "box_caption": "RiceSpike 0.495", "scores": {"class_score": 0.494873046875}, "domain": "pixel"}, {"position": {"minX": 532.6561889648438, "minY": 371.4117431640625, "maxX": 630.3438110351562, "maxY": 449.0882568359375}, "class_id": 0, "box_caption": "RiceSpike 0.493", "scores": {"class_score": 0.493408203125}, "domain": "pixel"}, {"position": {"minX": 546.3831787109375, "minY": 353.9126892089844, "maxX": 610.6168212890625, "maxY": 468.0873107910156}, "class_id": 0, "box_caption": "RiceSpike 0.490", "scores": {"class_score": 0.489501953125}, "domain": "pixel"}, {"position": {"minX": 519.7196655273438, "minY": 270.535400390625, "maxX": 643.2803344726562, "maxY": 333.964599609375}, "class_id": 0, "box_caption": "RiceSpike 0.476", "scores": {"class_score": 0.47607421875}, "domain": "pixel"}, {"position": {"minX": 842.5877685546875, "minY": 482.21173095703125, "maxX": 889.4122314453125, "maxY": 527.288330078125}, "class_id": 0, "box_caption": "RiceSpike 0.475", "scores": {"class_score": 0.47509765625}, "domain": "pixel"}, {"position": {"minX": 526.6427612304688, "minY": 368.57855224609375, "maxX": 632.3572387695312, "maxY": 451.42144775390625}, "class_id": 0, "box_caption": "RiceSpike 0.474", "scores": {"class_score": 0.474365234375}, "domain": "pixel"}, {"position": {"minX": 856.0203247070312, "minY": 93.7554702758789, "maxX": 882.9796752929688, "maxY": 104.8695297241211}, "class_id": 0, "box_caption": "RiceSpike 0.471", "scores": {"class_score": 0.471435546875}, "domain": "pixel"}, {"position": {"minX": 564.8609619140625, "minY": 329.36834716796875, "maxX": 587.1390380859375, "maxY": 409.63165283203125}, "class_id": 0, "box_caption": "RiceSpike 0.469", "scores": {"class_score": 0.46875}, "domain": "pixel"}, {"position": {"minX": 174.3153076171875, "minY": 508.71282958984375, "maxX": 287.6846923828125, "maxY": 545.2871704101562}, "class_id": 0, "box_caption": "RiceSpike 0.460", "scores": {"class_score": 0.4599609375}, "domain": "pixel"}, {"position": {"minX": 229.44744873046875, "minY": 525.3064575195312, "maxX": 291.55255126953125, "maxY": 554.6935424804688}, "class_id": 0, "box_caption": "RiceSpike 0.454", "scores": {"class_score": 0.453857421875}, "domain": "pixel"}, {"position": {"minX": 181.27987670898438, "minY": 488.54595947265625, "maxX": 277.7201232910156, "maxY": 563.4540405273438}, "class_id": 0, "box_caption": "RiceSpike 0.441", "scores": {"class_score": 0.44091796875}, "domain": "pixel"}, {"position": {"minX": 425.5945129394531, "minY": 509.6734619140625, "maxX": 474.4054870605469, "maxY": 526.3265380859375}, "class_id": 0, "box_caption": "RiceSpike 0.432", "scores": {"class_score": 0.431640625}, "domain": "pixel"}, {"position": {"minX": 266.8634338378906, "minY": 201.8372039794922, "maxX": 313.6365661621094, "maxY": 209.4127960205078}, "class_id": 0, "box_caption": "RiceSpike 0.425", "scores": {"class_score": 0.4248046875}, "domain": "pixel"}, {"position": {"minX": 781.6605224609375, "minY": 290.0902404785156, "maxX": 820.3394775390625, "maxY": 299.9097595214844}, "class_id": 0, "box_caption": "RiceSpike 0.408", "scores": {"class_score": 0.408203125}, "domain": "pixel"}, {"position": {"minX": 251.74713134765625, "minY": 262.93511962890625, "maxX": 324.25286865234375, "maxY": 301.06488037109375}, "class_id": 0, "box_caption": "RiceSpike 0.405", "scores": {"class_score": 0.40478515625}, "domain": "pixel"}, {"position": {"minX": 210.64654541015625, "minY": 260.849365234375, "maxX": 267.60345458984375, "maxY": 277.650634765625}, "class_id": 0, "box_caption": "RiceSpike 0.402", "scores": {"class_score": 0.40185546875}, "domain": "pixel"}, {"position": {"minX": 232.6402587890625, "minY": 528.8230590820312, "maxX": 291.3597412109375, "maxY": 550.1769409179688}, "class_id": 0, "box_caption": "RiceSpike 0.400", "scores": {"class_score": 0.400146484375}, "domain": "pixel"}, {"position": {"minX": 256.84967041015625, "minY": 254.19931030273438, "maxX": 319.65032958984375, "maxY": 311.8006896972656}, "class_id": 0, "box_caption": "RiceSpike 0.399", "scores": {"class_score": 0.399169921875}, "domain": "pixel"}, {"position": {"minX": 263.8560791015625, "minY": 244.02056884765625, "maxX": 310.1439208984375, "maxY": 322.97943115234375}, "class_id": 0, "box_caption": "RiceSpike 0.388", "scores": {"class_score": 0.388427734375}, "domain": "pixel"}, {"position": {"minX": 780.6883544921875, "minY": 280.58270263671875, "maxX": 818.3116455078125, "maxY": 311.41729736328125}, "class_id": 0, "box_caption": "RiceSpike 0.388", "scores": {"class_score": 0.38818359375}, "domain": "pixel"}, {"position": {"minX": 251.139892578125, "minY": 482.7293701171875, "maxX": 410.860107421875, "maxY": 526.7706298828125}, "class_id": 0, "box_caption": "RiceSpike 0.386", "scores": {"class_score": 0.38623046875}, "domain": "pixel"}, {"position": {"minX": 210.76480102539062, "minY": 262.6175231933594, "maxX": 266.9851989746094, "maxY": 277.8824768066406}, "class_id": 0, "box_caption": "RiceSpike 0.380", "scores": {"class_score": 0.380126953125}, "domain": "pixel"}, {"position": {"minX": 617.1506958007812, "minY": 506.95880126953125, "maxX": 647.8493041992188, "maxY": 581.0411987304688}, "class_id": 0, "box_caption": "RiceSpike 0.374", "scores": {"class_score": 0.373779296875}, "domain": "pixel"}, {"position": {"minX": 425.06463623046875, "minY": 497.67138671875, "maxX": 473.93536376953125, "maxY": 538.32861328125}, "class_id": 0, "box_caption": "RiceSpike 0.372", "scores": {"class_score": 0.372314453125}, "domain": "pixel"}, {"position": {"minX": 470.87255859375, "minY": 357.74420166015625, "maxX": 500.62744140625, "maxY": 393.75579833984375}, "class_id": 0, "box_caption": "RiceSpike 0.371", "scores": {"class_score": 0.37060546875}, "domain": "pixel"}, {"position": {"minX": 465.56500244140625, "minY": 360.78045654296875, "maxX": 502.43499755859375, "maxY": 387.21954345703125}, "class_id": 0, "box_caption": "RiceSpike 0.370", "scores": {"class_score": 0.370361328125}, "domain": "pixel"}, {"position": {"minX": 1010.1722412109375, "minY": 472.81842041015625, "maxX": 1039.8277587890625, "maxY": 521.1815795898438}, "class_id": 0, "box_caption": "RiceSpike 0.358", "scores": {"class_score": 0.35791015625}, "domain": "pixel"}, {"position": {"minX": 439.38262939453125, "minY": 492.87591552734375, "maxX": 459.11737060546875, "maxY": 542.1240844726562}, "class_id": 0, "box_caption": "RiceSpike 0.356", "scores": {"class_score": 0.356201171875}, "domain": "pixel"}, {"position": {"minX": 374.7853088378906, "minY": 370.95062255859375, "maxX": 450.2146911621094, "maxY": 396.54937744140625}, "class_id": 0, "box_caption": "RiceSpike 0.351", "scores": {"class_score": 0.35107421875}, "domain": "pixel"}, {"position": {"minX": 551.9535522460938, "minY": 325.46429443359375, "maxX": 604.0464477539062, "maxY": 410.53570556640625}, "class_id": 0, "box_caption": "RiceSpike 0.347", "scores": {"class_score": 0.346923828125}, "domain": "pixel"}, {"position": {"minX": 558.7843017578125, "minY": 333.83929443359375, "maxX": 596.2156982421875, "maxY": 404.66070556640625}, "class_id": 0, "box_caption": "RiceSpike 0.342", "scores": {"class_score": 0.342041015625}, "domain": "pixel"}, {"position": {"minX": 382.1134338378906, "minY": 356.6134338378906, "maxX": 436.8865661621094, "maxY": 411.3865661621094}, "class_id": 0, "box_caption": "RiceSpike 0.332", "scores": {"class_score": 0.33203125}, "domain": "pixel"}, {"position": {"minX": 538.0855102539062, "minY": 371.495849609375, "maxX": 581.9144897460938, "maxY": 519.504150390625}, "class_id": 0, "box_caption": "RiceSpike 0.318", "scores": {"class_score": 0.318115234375}, "domain": "pixel"}, {"position": {"minX": 463.5954284667969, "minY": 367.1510925292969, "maxX": 505.9045715332031, "maxY": 384.3489074707031}, "class_id": 0, "box_caption": "RiceSpike 0.316", "scores": {"class_score": 0.31591796875}, "domain": "pixel"}, {"position": {"minX": 618.9359130859375, "minY": 548.6271362304688, "maxX": 630.0640869140625, "maxY": 576.3728637695312}, "class_id": 0, "box_caption": "RiceSpike 0.294", "scores": {"class_score": 0.29443359375}, "domain": "pixel"}, {"position": {"minX": 809.7193603515625, "minY": 274.18548583984375, "maxX": 866.2806396484375, "maxY": 294.81451416015625}, "class_id": 0, "box_caption": "RiceSpike 0.287", "scores": {"class_score": 0.287109375}, "domain": "pixel"}, {"position": {"minX": 376.3320007324219, "minY": 368.42877197265625, "maxX": 461.1679992675781, "maxY": 394.57122802734375}, "class_id": 0, "box_caption": "RiceSpike 0.282", "scores": {"class_score": 0.282470703125}, "domain": "pixel"}, {"position": {"minX": 190.70681762695312, "minY": 500.86724853515625, "maxX": 283.043212890625, "maxY": 547.1327514648438}, "class_id": 0, "box_caption": "RiceSpike 0.277", "scores": {"class_score": 0.27685546875}, "domain": "pixel"}, {"position": {"minX": 250.79550170898438, "minY": 435.85711669921875, "maxX": 400.7044982910156, "maxY": 577.1428833007812}, "class_id": 0, "box_caption": "RiceSpike 0.246", "scores": {"class_score": 0.2457275390625}, "domain": "pixel"}, {"position": {"minX": 258.6168212890625, "minY": 250.88734436035156, "maxX": 326.8831787109375, "maxY": 311.6126708984375}, "class_id": 0, "box_caption": "RiceSpike 0.242", "scores": {"class_score": 0.242431640625}, "domain": "pixel"}, {"position": {"minX": 137.75885009765625, "minY": 115.83790588378906, "maxX": 224.99114990234375, "maxY": 133.03709411621094}, "class_id": 0, "box_caption": "RiceSpike 0.238", "scores": {"class_score": 0.23828125}, "domain": "pixel"}, {"position": {"minX": 10.295440673828125, "minY": 405.2733154296875, "maxX": 74.89205932617188, "maxY": 434.2266845703125}, "class_id": 0, "box_caption": "RiceSpike 0.231", "scores": {"class_score": 0.2310791015625}, "domain": "pixel"}, {"position": {"minX": 646.06298828125, "minY": 96.7254638671875, "maxX": 680.93701171875, "maxY": 104.7745361328125}, "class_id": 0, "box_caption": "RiceSpike 0.227", "scores": {"class_score": 0.2266845703125}, "domain": "pixel"}, {"position": {"minX": 10.290298461914062, "minY": 416.594482421875, "maxX": 74.83470153808594, "maxY": 424.405517578125}, "class_id": 0, "box_caption": "RiceSpike 0.222", "scores": {"class_score": 0.22216796875}, "domain": "pixel"}, {"position": {"minX": 558.7529296875, "minY": 354.30126953125, "maxX": 608.2470703125, "maxY": 464.69873046875}, "class_id": 0, "box_caption": "RiceSpike 0.212", "scores": {"class_score": 0.211669921875}, "domain": "pixel"}, {"position": {"minX": 235.1322021484375, "minY": 280.8968811035156, "maxX": 322.8677978515625, "maxY": 293.1031188964844}, "class_id": 0, "box_caption": "RiceSpike 0.211", "scores": {"class_score": 0.211181640625}, "domain": "pixel"}, {"position": {"minX": 517.295654296875, "minY": 345.9820556640625, "maxX": 623.704345703125, "maxY": 495.0179443359375}, "class_id": 0, "box_caption": "RiceSpike 0.200", "scores": {"class_score": 0.2003173828125}, "domain": "pixel"}, {"position": {"minX": 278.5714416503906, "minY": 396.8312683105469, "maxX": 346.9285583496094, "maxY": 423.1687316894531}, "class_id": 0, "box_caption": "RiceSpike 0.195", "scores": {"class_score": 0.19482421875}, "domain": "pixel"}, {"position": {"minX": 825.3512573242188, "minY": 258.8396911621094, "maxX": 868.6487426757812, "maxY": 298.1603088378906}, "class_id": 0, "box_caption": "RiceSpike 0.186", "scores": {"class_score": 0.1864013671875}, "domain": "pixel"}, {"position": {"minX": 454.2956237792969, "minY": 97.4241714477539, "maxX": 489.2043762207031, "maxY": 105.5758285522461}, "class_id": 0, "box_caption": "RiceSpike 0.173", "scores": {"class_score": 0.172607421875}, "domain": "pixel"}, {"position": {"minX": 254.625, "minY": 275.15625, "maxX": 331.375, "maxY": 281.84375}, "class_id": 0, "box_caption": "RiceSpike 0.166", "scores": {"class_score": 0.1663818359375}, "domain": "pixel"}, {"position": {"minX": 475.2281494140625, "minY": 358.0963439941406, "maxX": 494.2718505859375, "maxY": 395.9036560058594}, "class_id": 0, "box_caption": "RiceSpike 0.160", "scores": {"class_score": 0.1600341796875}, "domain": "pixel"}, {"position": {"minX": 861.775634765625, "minY": 79.76953887939453, "maxX": 894.224365234375, "maxY": 97.73046112060547}, "class_id": 0, "box_caption": "RiceSpike 0.151", "scores": {"class_score": 0.1505126953125}, "domain": "pixel"}, {"position": {"minX": 311.8468322753906, "minY": 48.448020935058594, "maxX": 417.1531677246094, "maxY": 121.4269790649414}, "class_id": 0, "box_caption": "RiceSpike 0.131", "scores": {"class_score": 0.130859375}, "domain": "pixel"}, {"position": {"minX": 806.7498168945312, "minY": 566.0863647460938, "maxX": 839.2501831054688, "maxY": 592.9136352539062}, "class_id": 0, "box_caption": "RiceSpike 0.121", "scores": {"class_score": 0.12139892578125}, "domain": "pixel"}, {"position": {"minX": 444.4046936035156, "minY": 387.57415771484375, "maxX": 483.0953063964844, "maxY": 540.4258422851562}, "class_id": 0, "box_caption": "RiceSpike 0.119", "scores": {"class_score": 0.1190185546875}, "domain": "pixel"}, {"position": {"minX": 819.1104125976562, "minY": 102.46489715576172, "maxX": 863.8895874023438, "maxY": 121.41010284423828}, "class_id": 0, "box_caption": "RiceSpike 0.116", "scores": {"class_score": 0.116455078125}, "domain": "pixel"}, {"position": {"minX": 810.4024658203125, "minY": 563.9827270507812, "maxX": 830.5975341796875, "maxY": 594.0172729492188}, "class_id": 0, "box_caption": "RiceSpike 0.115", "scores": {"class_score": 0.11492919921875}, "domain": "pixel"}, {"position": {"minX": 891.1511840820312, "minY": 99.00270080566406, "maxX": 907.8488159179688, "maxY": 114.74729919433594}, "class_id": 0, "box_caption": "RiceSpike 0.114", "scores": {"class_score": 0.11395263671875}, "domain": "pixel"}, {"position": {"minX": 487.63873291015625, "minY": 404.5849914550781, "maxX": 649.3612670898438, "maxY": 451.9150085449219}, "class_id": 0, "box_caption": "RiceSpike 0.113", "scores": {"class_score": 0.11285400390625}, "domain": "pixel"}, {"position": {"minX": 383.90069580078125, "minY": 293.2418212890625, "maxX": 422.59930419921875, "maxY": 300.2581787109375}, "class_id": 0, "box_caption": "RiceSpike 0.109", "scores": {"class_score": 0.10894775390625}, "domain": "pixel"}, {"position": {"minX": 387.24298095703125, "minY": 286.7281188964844, "maxX": 419.25701904296875, "maxY": 308.2718811035156}, "class_id": 0, "box_caption": "RiceSpike 0.107", "scores": {"class_score": 0.10723876953125}, "domain": "pixel"}, {"position": {"minX": 69.515625, "minY": 266.4453125, "maxX": 95.109375, "maxY": 273.0546875}, "class_id": 0, "box_caption": "RiceSpike 0.102", "scores": {"class_score": 0.102294921875}, "domain": "pixel"}, {"position": {"minX": 386.7135925292969, "minY": 287.20916748046875, "maxX": 421.2864074707031, "maxY": 308.29083251953125}, "class_id": 0, "box_caption": "RiceSpike 0.102", "scores": {"class_score": 0.10150146484375}, "domain": "pixel"}, {"position": {"minX": 20.313997268676758, "minY": 391.2514953613281, "maxX": 74.31100463867188, "maxY": 445.2485046386719}, "class_id": 0, "box_caption": "RiceSpike 0.100", "scores": {"class_score": 0.10015869140625}, "domain": "pixel"}, {"position": {"minX": 186.74176025390625, "minY": 536.349609375, "maxX": 224.50823974609375, "maxY": 543.650390625}, "class_id": 0, "box_caption": "RiceSpike 0.090", "scores": {"class_score": 0.09014892578125}, "domain": "pixel"}, {"position": {"minX": 814.9183349609375, "minY": 559.789306640625, "maxX": 830.0816650390625, "maxY": 597.210693359375}, "class_id": 0, "box_caption": "RiceSpike 0.089", "scores": {"class_score": 0.0894775390625}, "domain": "pixel"}, {"position": {"minX": 603.1282958984375, "minY": 499.4419250488281, "maxX": 648.8717041015625, "maxY": 585.55810546875}, "class_id": 0, "box_caption": "RiceSpike 0.088", "scores": {"class_score": 0.08807373046875}, "domain": "pixel"}, {"position": {"minX": 603.4694213867188, "minY": 542.1212158203125, "maxX": 646.5305786132812, "maxY": 576.8787841796875}, "class_id": 0, "box_caption": "RiceSpike 0.082", "scores": {"class_score": 0.08245849609375}, "domain": "pixel"}, {"position": {"minX": 847.27978515625, "minY": 384.6322937011719, "maxX": 860.72021484375, "maxY": 398.8677062988281}, "class_id": 0, "box_caption": "RiceSpike 0.082", "scores": {"class_score": 0.08172607421875}, "domain": "pixel"}, {"position": {"minX": 234.08935546875, "minY": 243.36126708984375, "maxX": 247.66064453125, "maxY": 295.13873291015625}, "class_id": 0, "box_caption": "RiceSpike 0.081", "scores": {"class_score": 0.080810546875}, "domain": "pixel"}, {"position": {"minX": 230.53060913085938, "minY": 243.18154907226562, "maxX": 250.46939086914062, "maxY": 295.8184509277344}, "class_id": 0, "box_caption": "RiceSpike 0.078", "scores": {"class_score": 0.07818603515625}, "domain": "pixel"}, {"position": {"minX": 1017.243408203125, "minY": 466.63800048828125, "maxX": 1044.756591796875, "maxY": 490.36199951171875}, "class_id": 0, "box_caption": "RiceSpike 0.078", "scores": {"class_score": 0.07757568359375}, "domain": "pixel"}, {"position": {"minX": 393.334716796875, "minY": 472.1272277832031, "maxX": 458.165283203125, "maxY": 485.8727722167969}, "class_id": 0, "box_caption": "RiceSpike 0.076", "scores": {"class_score": 0.07574462890625}, "domain": "pixel"}, {"position": {"minX": 842.6956787109375, "minY": 91.739013671875, "maxX": 863.3043212890625, "maxY": 100.760986328125}, "class_id": 0, "box_caption": "RiceSpike 0.068", "scores": {"class_score": 0.0679931640625}, "domain": "pixel"}, {"position": {"minX": 198.33851623535156, "minY": 37.859317779541016, "maxX": 230.91148376464844, "maxY": 42.890682220458984}, "class_id": 0, "box_caption": "RiceSpike 0.067", "scores": {"class_score": 0.06719970703125}, "domain": "pixel"}, {"position": {"minX": 805.3402709960938, "minY": 573.5288696289062, "maxX": 836.6597290039062, "maxY": 583.4711303710938}, "class_id": 0, "box_caption": "RiceSpike 0.064", "scores": {"class_score": 0.0635986328125}, "domain": "pixel"}, {"position": {"minX": 90.99896240234375, "minY": 410.2486572265625, "maxX": 143.87603759765625, "maxY": 440.7513427734375}, "class_id": 0, "box_caption": "RiceSpike 0.062", "scores": {"class_score": 0.0618896484375}, "domain": "pixel"}, {"position": {"minX": 635.6879272460938, "minY": 507.889404296875, "maxX": 647.3120727539062, "maxY": 540.110595703125}, "class_id": 0, "box_caption": "RiceSpike 0.062", "scores": {"class_score": 0.06170654296875}, "domain": "pixel"}, {"position": {"minX": 383.6441955566406, "minY": 480.3401184082031, "maxX": 483.8558044433594, "maxY": 498.6598815917969}, "class_id": 0, "box_caption": "RiceSpike 0.059", "scores": {"class_score": 0.059234619140625}, "domain": "pixel"}, {"position": {"minX": 837.1589965820312, "minY": 496.04180908203125, "maxX": 879.8410034179688, "maxY": 525.9581909179688}, "class_id": 0, "box_caption": "RiceSpike 0.059", "scores": {"class_score": 0.059051513671875}, "domain": "pixel"}, {"position": {"minX": 24.60799789428711, "minY": 49.502037048339844, "maxX": 105.51699829101562, "maxY": 98.99796295166016}, "class_id": 0, "box_caption": "RiceSpike 0.055", "scores": {"class_score": 0.05499267578125}, "domain": "pixel"}, {"position": {"minX": 187.3499755859375, "minY": 377.1206359863281, "maxX": 280.4000244140625, "maxY": 438.3793640136719}, "class_id": 0, "box_caption": "RiceSpike 0.053", "scores": {"class_score": 0.053009033203125}, "domain": "pixel"}, {"position": {"minX": 617.01318359375, "minY": 81.87779998779297, "maxX": 663.98681640625, "maxY": 94.12220001220703}, "class_id": 0, "box_caption": "RiceSpike 0.050", "scores": {"class_score": 0.049560546875}, "domain": "pixel"}, {"position": {"minX": 541.0331420898438, "minY": 345.7030944824219, "maxX": 605.9668579101562, "maxY": 401.7969055175781}, "class_id": 0, "box_caption": "RiceSpike 0.048", "scores": {"class_score": 0.048248291015625}, "domain": "pixel"}, {"position": {"minX": 865.6544189453125, "minY": 99.75857543945312, "maxX": 900.3455810546875, "maxY": 110.86642456054688}, "class_id": 0, "box_caption": "RiceSpike 0.047", "scores": {"class_score": 0.04736328125}, "domain": "pixel"}, {"position": {"minX": 606.0942993164062, "minY": 62.01897430419922, "maxX": 638.9057006835938, "maxY": 89.23102569580078}, "class_id": 0, "box_caption": "RiceSpike 0.045", "scores": {"class_score": 0.045257568359375}, "domain": "pixel"}, {"position": {"minX": 278.81671142578125, "minY": 194.6062469482422, "maxX": 331.68328857421875, "maxY": 212.6437530517578}, "class_id": 0, "box_caption": "RiceSpike 0.045", "scores": {"class_score": 0.04498291015625}, "domain": "pixel"}, {"position": {"minX": 16.3480224609375, "minY": 406.4122619628906, "maxX": 82.9644775390625, "maxY": 418.5877380371094}, "class_id": 0, "box_caption": "RiceSpike 0.045", "scores": {"class_score": 0.044677734375}, "domain": "pixel"}, {"position": {"minX": 317.9233703613281, "minY": 411.0924072265625, "maxX": 359.0766296386719, "maxY": 575.4075927734375}, "class_id": 0, "box_caption": "RiceSpike 0.043", "scores": {"class_score": 0.042694091796875}, "domain": "pixel"}, {"position": {"minX": 1009.8055419921875, "minY": 98.53089904785156, "maxX": 1027.1944580078125, "maxY": 120.09410095214844}, "class_id": 0, "box_caption": "RiceSpike 0.042", "scores": {"class_score": 0.041961669921875}, "domain": "pixel"}, {"position": {"minX": 237.75, "minY": 289.89453125, "maxX": 310.75, "maxY": 301.60546875}, "class_id": 0, "box_caption": "RiceSpike 0.040", "scores": {"class_score": 0.04034423828125}, "domain": "pixel"}, {"position": {"minX": 393.449462890625, "minY": 460.04669189453125, "maxX": 448.550537109375, "maxY": 496.45330810546875}, "class_id": 0, "box_caption": "RiceSpike 0.040", "scores": {"class_score": 0.039642333984375}, "domain": "pixel"}, {"position": {"minX": 925.7769775390625, "minY": 561.6746826171875, "maxX": 948.2230224609375, "maxY": 587.3253173828125}, "class_id": 0, "box_caption": "RiceSpike 0.039", "scores": {"class_score": 0.038726806640625}, "domain": "pixel"}, {"position": {"minX": 288.88812255859375, "minY": 232.57998657226562, "maxX": 303.11187744140625, "maxY": 322.4200134277344}, "class_id": 0, "box_caption": "RiceSpike 0.038", "scores": {"class_score": 0.038299560546875}, "domain": "pixel"}, {"position": {"minX": 853.2371215820312, "minY": 115.83236694335938, "maxX": 884.7628784179688, "maxY": 125.29263305664062}, "class_id": 0, "box_caption": "RiceSpike 0.038", "scores": {"class_score": 0.037994384765625}, "domain": "pixel"}, {"position": {"minX": 569.996826171875, "minY": 282.53125, "maxX": 621.003173828125, "maxY": 294.96875}, "class_id": 0, "box_caption": "RiceSpike 0.037", "scores": {"class_score": 0.037200927734375}, "domain": "pixel"}, {"position": {"minX": 216.61544799804688, "minY": 506.88067626953125, "maxX": 278.8845520019531, "maxY": 525.1193237304688}, "class_id": 0, "box_caption": "RiceSpike 0.037", "scores": {"class_score": 0.036865234375}, "domain": "pixel"}, {"position": {"minX": 622.4483642578125, "minY": 506.376953125, "maxX": 653.5516357421875, "maxY": 559.623046875}, "class_id": 0, "box_caption": "RiceSpike 0.036", "scores": {"class_score": 0.035797119140625}, "domain": "pixel"}, {"position": {"minX": 307.5208740234375, "minY": 434.73834228515625, "maxX": 383.9791259765625, "maxY": 550.7616577148438}, "class_id": 0, "box_caption": "RiceSpike 0.034", "scores": {"class_score": 0.034149169921875}, "domain": "pixel"}, {"position": {"minX": 1004.5809326171875, "minY": 478.54632568359375, "maxX": 1029.4190673828125, "maxY": 546.4536743164062}, "class_id": 0, "box_caption": "RiceSpike 0.033", "scores": {"class_score": 0.032958984375}, "domain": "pixel"}, {"position": {"minX": 304.2588195800781, "minY": 419.59637451171875, "maxX": 346.2411804199219, "maxY": 590.903564453125}, "class_id": 0, "box_caption": "RiceSpike 0.032", "scores": {"class_score": 0.03204345703125}, "domain": "pixel"}, {"position": {"minX": 260.51031494140625, "minY": 248.4805450439453, "maxX": 304.48968505859375, "maxY": 325.51947021484375}, "class_id": 0, "box_caption": "RiceSpike 0.031", "scores": {"class_score": 0.031494140625}, "domain": "pixel"}, {"position": {"minX": 395.44244384765625, "minY": 443.4615478515625, "maxX": 473.55755615234375, "maxY": 519.5384521484375}, "class_id": 0, "box_caption": "RiceSpike 0.031", "scores": {"class_score": 0.031463623046875}, "domain": "pixel"}, {"position": {"minX": 484.7333984375, "minY": 516.364501953125, "maxX": 510.7666015625, "maxY": 571.635498046875}, "class_id": 0, "box_caption": "RiceSpike 0.031", "scores": {"class_score": 0.031402587890625}, "domain": "pixel"}, {"position": {"minX": 98.65826416015625, "minY": 404.22796630859375, "maxX": 157.21673583984375, "maxY": 440.77203369140625}, "class_id": 0, "box_caption": "RiceSpike 0.031", "scores": {"class_score": 0.0307464599609375}, "domain": "pixel"}, {"position": {"minX": 480.66339111328125, "minY": 518.4625854492188, "maxX": 514.3366088867188, "maxY": 569.5374145507812}, "class_id": 0, "box_caption": "RiceSpike 0.030", "scores": {"class_score": 0.0296783447265625}, "domain": "pixel"}, {"position": {"minX": 279.7091979980469, "minY": 266.2080078125, "maxX": 371.7908020019531, "maxY": 327.7919921875}, "class_id": 0, "box_caption": "RiceSpike 0.030", "scores": {"class_score": 0.0296478271484375}, "domain": "pixel"}, {"position": {"minX": 242.50250244140625, "minY": 302.30596923828125, "maxX": 316.49749755859375, "maxY": 314.69403076171875}, "class_id": 0, "box_caption": "RiceSpike 0.030", "scores": {"class_score": 0.029571533203125}, "domain": "pixel"}, {"position": {"minX": 1013.21630859375, "minY": 387.04815673828125, "maxX": 1025.78369140625, "maxY": 405.95184326171875}, "class_id": 0, "box_caption": "RiceSpike 0.028", "scores": {"class_score": 0.0275115966796875}, "domain": "pixel"}, {"position": {"minX": 401.32904052734375, "minY": 277.5975036621094, "maxX": 412.17095947265625, "maxY": 316.4024963378906}, "class_id": 0, "box_caption": "RiceSpike 0.025", "scores": {"class_score": 0.0252532958984375}, "domain": "pixel"}, {"position": {"minX": 409.71209716796875, "minY": 410.65447998046875, "maxX": 530.7879028320312, "maxY": 528.3455200195312}, "class_id": 0, "box_caption": "RiceSpike 0.025", "scores": {"class_score": 0.0250701904296875}, "domain": "pixel"}, {"position": {"minX": 184.61758422851562, "minY": 536.799560546875, "maxX": 211.88241577148438, "maxY": 551.200439453125}, "class_id": 0, "box_caption": "RiceSpike 0.025", "scores": {"class_score": 0.0246734619140625}, "domain": "pixel"}, {"position": {"minX": 472.65545654296875, "minY": 536.3704833984375, "maxX": 522.3445434570312, "maxY": 550.6295166015625}, "class_id": 0, "box_caption": "RiceSpike 0.024", "scores": {"class_score": 0.023956298828125}, "domain": "pixel"}, {"position": {"minX": 312.8241271972656, "minY": 416.20489501953125, "maxX": 397.6758728027344, "maxY": 556.7951049804688}, "class_id": 0, "box_caption": "RiceSpike 0.022", "scores": {"class_score": 0.0224456787109375}, "domain": "pixel"}, {"position": {"minX": 154.218017578125, "minY": 107.42112731933594, "maxX": 215.781982421875, "maxY": 146.45387268066406}, "class_id": 0, "box_caption": "RiceSpike 0.022", "scores": {"class_score": 0.0222625732421875}, "domain": "pixel"}, {"position": {"minX": 471.5635681152344, "minY": 348.7808837890625, "maxX": 508.4364318847656, "maxY": 397.2191162109375}, "class_id": 0, "box_caption": "RiceSpike 0.022", "scores": {"class_score": 0.0218048095703125}, "domain": "pixel"}, {"position": {"minX": 16.61712074279785, "minY": 417.32086181640625, "maxX": 64.63288116455078, "maxY": 433.67913818359375}, "class_id": 0, "box_caption": "RiceSpike 0.021", "scores": {"class_score": 0.0211029052734375}, "domain": "pixel"}, {"position": {"minX": 220.39178466796875, "minY": 525.6292724609375, "maxX": 299.10821533203125, "maxY": 541.3707275390625}, "class_id": 0, "box_caption": "RiceSpike 0.021", "scores": {"class_score": 0.02093505859375}, "domain": "pixel"}, {"position": {"minX": 987.34033203125, "minY": 490.1995849609375, "maxX": 1048.65966796875, "maxY": 533.8004150390625}, "class_id": 0, "box_caption": "RiceSpike 0.020", "scores": {"class_score": 0.02044677734375}, "domain": "pixel"}, {"position": {"minX": 257.256103515625, "minY": 16.89836883544922, "maxX": 300.243896484375, "maxY": 32.44538116455078}, "class_id": 0, "box_caption": "RiceSpike 0.020", "scores": {"class_score": 0.020172119140625}, "domain": "pixel"}, {"position": {"minX": 415.503662109375, "minY": 428.7628173828125, "maxX": 536.996337890625, "maxY": 496.2371826171875}, "class_id": 0, "box_caption": "RiceSpike 0.019", "scores": {"class_score": 0.0193328857421875}, "domain": "pixel"}, {"position": {"minX": 295.20074462890625, "minY": 418.88714599609375, "maxX": 357.29925537109375, "maxY": 587.1128540039062}, "class_id": 0, "box_caption": "RiceSpike 0.018", "scores": {"class_score": 0.0177459716796875}, "domain": "pixel"}, {"position": {"minX": 878.26416015625, "minY": 62.97962951660156, "maxX": 885.73583984375, "maxY": 88.39537048339844}, "class_id": 0, "box_caption": "RiceSpike 0.017", "scores": {"class_score": 0.016876220703125}, "domain": "pixel"}, {"position": {"minX": 787.9607543945312, "minY": 285.1493225097656, "maxX": 832.0392456054688, "maxY": 294.8506774902344}, "class_id": 0, "box_caption": "RiceSpike 0.016", "scores": {"class_score": 0.0163726806640625}, "domain": "pixel"}, {"position": {"minX": 47.71595764160156, "minY": 52.295127868652344, "maxX": 154.28404235839844, "maxY": 73.82987976074219}, "class_id": 0, "box_caption": "RiceSpike 0.016", "scores": {"class_score": 0.0162506103515625}, "domain": "pixel"}, {"position": {"minX": 146.06773376464844, "minY": 122.42495727539062, "maxX": 190.18226623535156, "maxY": 140.82504272460938}, "class_id": 0, "box_caption": "RiceSpike 0.016", "scores": {"class_score": 0.0160980224609375}, "domain": "pixel"}, {"position": {"minX": 243.216552734375, "minY": 302.7425231933594, "maxX": 275.283447265625, "maxY": 328.7574768066406}, "class_id": 0, "box_caption": "RiceSpike 0.015", "scores": {"class_score": 0.015350341796875}, "domain": "pixel"}, {"position": {"minX": 461.822998046875, "minY": 81.38849639892578, "maxX": 477.177001953125, "maxY": 117.23650360107422}, "class_id": 0, "box_caption": "RiceSpike 0.015", "scores": {"class_score": 0.01505279541015625}, "domain": "pixel"}, {"position": {"minX": 469.047607421875, "minY": 524.162109375, "maxX": 518.452392578125, "maxY": 568.837890625}, "class_id": 0, "box_caption": "RiceSpike 0.015", "scores": {"class_score": 0.01491546630859375}, "domain": "pixel"}, {"position": {"minX": 240.58108520507812, "minY": 514.052490234375, "maxX": 367.9189147949219, "maxY": 533.947509765625}, "class_id": 0, "box_caption": "RiceSpike 0.015", "scores": {"class_score": 0.01451873779296875}, "domain": "pixel"}, {"position": {"minX": 802.6729736328125, "minY": 232.11439514160156, "maxX": 837.3270263671875, "maxY": 245.63560485839844}, "class_id": 0, "box_caption": "RiceSpike 0.014", "scores": {"class_score": 0.014495849609375}, "domain": "pixel"}, {"position": {"minX": 397.7605285644531, "minY": 361.0203552246094, "maxX": 461.2394714355469, "maxY": 389.9796447753906}, "class_id": 0, "box_caption": "RiceSpike 0.014", "scores": {"class_score": 0.01445770263671875}, "domain": "pixel"}, {"position": {"minX": 397.025634765625, "minY": 452.5210876464844, "maxX": 470.474365234375, "maxY": 509.9789123535156}, "class_id": 0, "box_caption": "RiceSpike 0.014", "scores": {"class_score": 0.0138092041015625}, "domain": "pixel"}, {"position": {"minX": 253.52899169921875, "minY": 504.31463623046875, "maxX": 314.97100830078125, "maxY": 572.6853637695312}, "class_id": 0, "box_caption": "RiceSpike 0.013", "scores": {"class_score": 0.01324462890625}, "domain": "pixel"}, {"position": {"minX": 274.00909423828125, "minY": 492.9150390625, "maxX": 295.49090576171875, "maxY": 584.0849609375}, "class_id": 0, "box_caption": "RiceSpike 0.013", "scores": {"class_score": 0.01317596435546875}, "domain": "pixel"}, {"position": {"minX": 297.27960205078125, "minY": 239.7620849609375, "maxX": 353.72039794921875, "maxY": 343.2379150390625}, "class_id": 0, "box_caption": "RiceSpike 0.013", "scores": {"class_score": 0.01287078857421875}, "domain": "pixel"}, {"position": {"minX": 12.687461853027344, "minY": 397.0937194824219, "maxX": 60.500038146972656, "maxY": 444.9062805175781}, "class_id": 0, "box_caption": "RiceSpike 0.013", "scores": {"class_score": 0.0128021240234375}, "domain": "pixel"}, {"position": {"minX": 529.849609375, "minY": 111.18330383300781, "maxX": 608.150390625, "maxY": 161.8166961669922}, "class_id": 0, "box_caption": "RiceSpike 0.012", "scores": {"class_score": 0.01245880126953125}, "domain": "pixel"}, {"position": {"minX": 215.36434936523438, "minY": 256.705810546875, "maxX": 277.1356506347656, "maxY": 277.294189453125}, "class_id": 0, "box_caption": "RiceSpike 0.012", "scores": {"class_score": 0.012176513671875}, "domain": "pixel"}, {"position": {"minX": 807.1554565429688, "minY": 222.4807586669922, "maxX": 833.8445434570312, "maxY": 254.7692413330078}, "class_id": 0, "box_caption": "RiceSpike 0.012", "scores": {"class_score": 0.01171112060546875}, "domain": "pixel"}, {"position": {"minX": 243.0496826171875, "minY": 310.7583312988281, "maxX": 306.4503173828125, "maxY": 323.7416687011719}, "class_id": 0, "box_caption": "RiceSpike 0.011", "scores": {"class_score": 0.0114593505859375}, "domain": "pixel"}, {"position": {"minX": 379.23248291015625, "minY": 371.72247314453125, "maxX": 424.76751708984375, "maxY": 405.77752685546875}, "class_id": 0, "box_caption": "RiceSpike 0.011", "scores": {"class_score": 0.01100921630859375}, "domain": "pixel"}, {"position": {"minX": 511.1700439453125, "minY": 303.54486083984375, "maxX": 627.8299560546875, "maxY": 352.45513916015625}, "class_id": 0, "box_caption": "RiceSpike 0.011", "scores": {"class_score": 0.01094818115234375}, "domain": "pixel"}, {"position": {"minX": 395.1976013183594, "minY": 361.0607604980469, "maxX": 407.3023986816406, "maxY": 416.9392395019531}, "class_id": 0, "box_caption": "RiceSpike 0.011", "scores": {"class_score": 0.01087188720703125}, "domain": "pixel"}, {"position": {"minX": 1007.3797607421875, "minY": 383.3060607910156, "maxX": 1032.6202392578125, "maxY": 403.1939392089844}, "class_id": 0, "box_caption": "RiceSpike 0.011", "scores": {"class_score": 0.01084136962890625}, "domain": "pixel"}, {"position": {"minX": 598.0279541015625, "minY": 528.362548828125, "maxX": 651.9720458984375, "maxY": 571.637451171875}, "class_id": 0, "box_caption": "RiceSpike 0.011", "scores": {"class_score": 0.01067352294921875}, "domain": "pixel"}, {"position": {"minX": 27.33751678466797, "minY": 392.8172302246094, "maxX": 85.66248321533203, "maxY": 429.1827697753906}, "class_id": 0, "box_caption": "RiceSpike 0.011", "scores": {"class_score": 0.01059722900390625}, "domain": "pixel"}, {"position": {"minX": 900.4305419921875, "minY": 282.86468505859375, "maxX": 914.5694580078125, "maxY": 298.13531494140625}, "class_id": 0, "box_caption": "RiceSpike 0.010", "scores": {"class_score": 0.01032257080078125}, "domain": "pixel"}, {"position": {"minX": 550.6348876953125, "minY": 393.66082763671875, "maxX": 625.3651123046875, "maxY": 409.83917236328125}, "class_id": 0, "box_caption": "RiceSpike 0.010", "scores": {"class_score": 0.01018524169921875}, "domain": "pixel"}, {"position": {"minX": 270.6493835449219, "minY": 497.99957275390625, "maxX": 315.3506164550781, "maxY": 568.0004272460938}, "class_id": 0, "box_caption": "RiceSpike 0.010", "scores": {"class_score": 0.01018524169921875}, "domain": "pixel"}], "class_labels": {"0": "RiceSpike", "1": "none"}}