{"box_data": [{"position": {"minX": 245.2215576171875, "minY": 454.0793151855469, "maxX": 318.7784423828125, "maxY": 466.4206848144531}, "class_id": 0, "box_caption": "RiceSpike 0.819", "scores": {"class_score": 0.81884765625}, "domain": "pixel"}, {"position": {"minX": 455.282470703125, "minY": 428.5104675292969, "maxX": 500.717529296875, "maxY": 470.9895324707031}, "class_id": 0, "box_caption": "RiceSpike 0.727", "scores": {"class_score": 0.72705078125}, "domain": "pixel"}, {"position": {"minX": 336.524169921875, "minY": 252.69161987304688, "maxX": 453.475830078125, "maxY": 332.3083801269531}, "class_id": 0, "box_caption": "RiceSpike 0.714", "scores": {"class_score": 0.71435546875}, "domain": "pixel"}, {"position": {"minX": 331.2288513183594, "minY": 428.534423828125, "maxX": 420.2711486816406, "maxY": 473.965576171875}, "class_id": 0, "box_caption": "RiceSpike 0.687", "scores": {"class_score": 0.6865234375}, "domain": "pixel"}, {"position": {"minX": 321.29034423828125, "minY": 528.5697631835938, "maxX": 452.20965576171875, "maxY": 581.4302368164062}, "class_id": 0, "box_caption": "RiceSpike 0.686", "scores": {"class_score": 0.685546875}, "domain": "pixel"}, {"position": {"minX": 49.922630310058594, "minY": 489.63507080078125, "maxX": 213.82736206054688, "maxY": 524.8648681640625}, "class_id": 0, "box_caption": "RiceSpike 0.686", "scores": {"class_score": 0.685546875}, "domain": "pixel"}, {"position": {"minX": 340.74609375, "minY": 145.45526123046875, "maxX": 449.25390625, "maxY": 271.04473876953125}, "class_id": 0, "box_caption": "RiceSpike 0.680", "scores": {"class_score": 0.6796875}, "domain": "pixel"}, {"position": {"minX": 603.84228515625, "minY": 92.820556640625, "maxX": 654.15771484375, "maxY": 160.929443359375}, "class_id": 0, "box_caption": "RiceSpike 0.677", "scores": {"class_score": 0.6767578125}, "domain": "pixel"}, {"position": {"minX": 115.64801025390625, "minY": 167.357177734375, "maxX": 243.85198974609375, "maxY": 191.392822265625}, "class_id": 0, "box_caption": "RiceSpike 0.672", "scores": {"class_score": 0.671875}, "domain": "pixel"}, {"position": {"minX": 73.11799621582031, "minY": 384.8859558105469, "maxX": 248.8820037841797, "maxY": 465.6140441894531}, "class_id": 0, "box_caption": "RiceSpike 0.670", "scores": {"class_score": 0.669921875}, "domain": "pixel"}, {"position": {"minX": 17.742347717285156, "minY": 502.93359375, "maxX": 82.32015228271484, "maxY": 523.06640625}, "class_id": 0, "box_caption": "RiceSpike 0.667", "scores": {"class_score": 0.66748046875}, "domain": "pixel"}, {"position": {"minX": 284.3515625, "minY": 305.0504455566406, "maxX": 425.1484375, "maxY": 396.9495544433594}, "class_id": 0, "box_caption": "RiceSpike 0.667", "scores": {"class_score": 0.66650390625}, "domain": "pixel"}, {"position": {"minX": 73.3662109375, "minY": 393.7669372558594, "maxX": 248.6337890625, "maxY": 457.7330627441406}, "class_id": 0, "box_caption": "RiceSpike 0.665", "scores": {"class_score": 0.6650390625}, "domain": "pixel"}, {"position": {"minX": 19.503921508789062, "minY": 271.0513610839844, "maxX": 100.3710708618164, "maxY": 300.4486389160156}, "class_id": 0, "box_caption": "RiceSpike 0.664", "scores": {"class_score": 0.6640625}, "domain": "pixel"}, {"position": {"minX": 600.0174560546875, "minY": 233.44351196289062, "maxX": 642.9825439453125, "maxY": 243.30648803710938}, "class_id": 0, "box_caption": "RiceSpike 0.662", "scores": {"class_score": 0.662109375}, "domain": "pixel"}, {"position": {"minX": 63.45806884765625, "minY": 189.5894775390625, "maxX": 263.29193115234375, "maxY": 285.9105224609375}, "class_id": 0, "box_caption": "RiceSpike 0.653", "scores": {"class_score": 0.6533203125}, "domain": "pixel"}, {"position": {"minX": 519.7628173828125, "minY": 95.582275390625, "maxX": 571.2371826171875, "maxY": 167.917724609375}, "class_id": 0, "box_caption": "RiceSpike 0.640", "scores": {"class_score": 0.64013671875}, "domain": "pixel"}, {"position": {"minX": 9.576568603515625, "minY": 146.3905487060547, "maxX": 139.92343139648438, "maxY": 200.6094512939453}, "class_id": 0, "box_caption": "RiceSpike 0.640", "scores": {"class_score": 0.64013671875}, "domain": "pixel"}, {"position": {"minX": 310.4908447265625, "minY": 372.8233337402344, "maxX": 342.0091552734375, "maxY": 435.6766662597656}, "class_id": 0, "box_caption": "RiceSpike 0.629", "scores": {"class_score": 0.62939453125}, "domain": "pixel"}, {"position": {"minX": 33.05741882324219, "minY": 362.66455078125, "maxX": 133.0675811767578, "maxY": 375.33544921875}, "class_id": 0, "box_caption": "RiceSpike 0.628", "scores": {"class_score": 0.6279296875}, "domain": "pixel"}, {"position": {"minX": 147.34817504882812, "minY": 13.727081298828125, "maxX": 269.1518249511719, "maxY": 119.64791870117188}, "class_id": 0, "box_caption": "RiceSpike 0.627", "scores": {"class_score": 0.62744140625}, "domain": "pixel"}, {"position": {"minX": 331.04833984375, "minY": 423.056640625, "maxX": 421.95166015625, "maxY": 480.943359375}, "class_id": 0, "box_caption": "RiceSpike 0.622", "scores": {"class_score": 0.62158203125}, "domain": "pixel"}, {"position": {"minX": 36.90625, "minY": 366.30859375, "maxX": 135.96875, "maxY": 376.19140625}, "class_id": 0, "box_caption": "RiceSpike 0.593", "scores": {"class_score": 0.59326171875}, "domain": "pixel"}, {"position": {"minX": 13.862648010253906, "minY": 275.6109313964844, "maxX": 107.51234436035156, "maxY": 296.3890686035156}, "class_id": 0, "box_caption": "RiceSpike 0.589", "scores": {"class_score": 0.58935546875}, "domain": "pixel"}, {"position": {"minX": 333.7606201171875, "minY": 148.8856201171875, "maxX": 455.2393798828125, "maxY": 270.3643798828125}, "class_id": 0, "box_caption": "RiceSpike 0.575", "scores": {"class_score": 0.5751953125}, "domain": "pixel"}, {"position": {"minX": 121.96022033691406, "minY": 165.30076599121094, "maxX": 239.53977966308594, "maxY": 196.19923400878906}, "class_id": 0, "box_caption": "RiceSpike 0.573", "scores": {"class_score": 0.5732421875}, "domain": "pixel"}, {"position": {"minX": 12.821609497070312, "minY": 151.27479553222656, "maxX": 140.92840576171875, "maxY": 194.72520446777344}, "class_id": 0, "box_caption": "RiceSpike 0.572", "scores": {"class_score": 0.57177734375}, "domain": "pixel"}, {"position": {"minX": 954.3185424804688, "minY": 448.4564514160156, "maxX": 985.6814575195312, "maxY": 485.0435485839844}, "class_id": 0, "box_caption": "RiceSpike 0.556", "scores": {"class_score": 0.55615234375}, "domain": "pixel"}, {"position": {"minX": 316.8469543457031, "minY": 167.38778686523438, "maxX": 357.1530456542969, "maxY": 201.11221313476562}, "class_id": 0, "box_caption": "RiceSpike 0.543", "scores": {"class_score": 0.54296875}, "domain": "pixel"}, {"position": {"minX": 294.6500549316406, "minY": 567.8161010742188, "maxX": 345.3499450683594, "maxY": 576.1838989257812}, "class_id": 0, "box_caption": "RiceSpike 0.527", "scores": {"class_score": 0.52734375}, "domain": "pixel"}, {"position": {"minX": 329.676025390625, "minY": 427.3819580078125, "maxX": 425.823974609375, "maxY": 483.6180419921875}, "class_id": 0, "box_caption": "RiceSpike 0.523", "scores": {"class_score": 0.52294921875}, "domain": "pixel"}, {"position": {"minX": 49.2598876953125, "minY": 196.20928955078125, "maxX": 266.2401123046875, "maxY": 287.2907409667969}, "class_id": 0, "box_caption": "RiceSpike 0.520", "scores": {"class_score": 0.52001953125}, "domain": "pixel"}, {"position": {"minX": 273.6820068359375, "minY": 581.1560668945312, "maxX": 298.3179931640625, "maxY": 591.8439331054688}, "class_id": 0, "box_caption": "RiceSpike 0.514", "scores": {"class_score": 0.51416015625}, "domain": "pixel"}, {"position": {"minX": 599.7245483398438, "minY": 574.98193359375, "maxX": 621.2754516601562, "maxY": 590.01806640625}, "class_id": 0, "box_caption": "RiceSpike 0.508", "scores": {"class_score": 0.5078125}, "domain": "pixel"}, {"position": {"minX": 452.6352844238281, "minY": 430.8764343261719, "maxX": 499.8647155761719, "maxY": 474.1235656738281}, "class_id": 0, "box_caption": "RiceSpike 0.505", "scores": {"class_score": 0.50537109375}, "domain": "pixel"}, {"position": {"minX": 243.81362915039062, "minY": 455.4845275878906, "maxX": 321.1863708496094, "maxY": 471.0154724121094}, "class_id": 0, "box_caption": "RiceSpike 0.501", "scores": {"class_score": 0.50146484375}, "domain": "pixel"}, {"position": {"minX": 14.144775390625, "minY": 354.9090881347656, "maxX": 90.042724609375, "maxY": 403.0909118652344}, "class_id": 0, "box_caption": "RiceSpike 0.493", "scores": {"class_score": 0.4931640625}, "domain": "pixel"}, {"position": {"minX": 153.55667114257812, "minY": 370.92645263671875, "maxX": 332.4433288574219, "maxY": 430.57354736328125}, "class_id": 0, "box_caption": "RiceSpike 0.474", "scores": {"class_score": 0.47412109375}, "domain": "pixel"}, {"position": {"minX": 319.4411315917969, "minY": 536.0745239257812, "maxX": 451.5588684082031, "maxY": 581.9254760742188}, "class_id": 0, "box_caption": "RiceSpike 0.474", "scores": {"class_score": 0.4736328125}, "domain": "pixel"}, {"position": {"minX": 276.7859191894531, "minY": 304.41009521484375, "maxX": 434.7140808105469, "maxY": 406.58990478515625}, "class_id": 0, "box_caption": "RiceSpike 0.470", "scores": {"class_score": 0.469970703125}, "domain": "pixel"}, {"position": {"minX": 14.76251220703125, "minY": 274.9378967285156, "maxX": 103.11248779296875, "maxY": 303.0621032714844}, "class_id": 0, "box_caption": "RiceSpike 0.465", "scores": {"class_score": 0.465087890625}, "domain": "pixel"}, {"position": {"minX": 149.0953369140625, "minY": 376.0533752441406, "maxX": 339.4046630859375, "maxY": 435.4466247558594}, "class_id": 0, "box_caption": "RiceSpike 0.437", "scores": {"class_score": 0.436767578125}, "domain": "pixel"}, {"position": {"minX": 688.0147705078125, "minY": 576.9122314453125, "maxX": 703.9852294921875, "maxY": 591.0877685546875}, "class_id": 0, "box_caption": "RiceSpike 0.436", "scores": {"class_score": 0.435546875}, "domain": "pixel"}, {"position": {"minX": 100.06756591796875, "minY": 334.6722717285156, "maxX": 179.43243408203125, "maxY": 343.3277282714844}, "class_id": 0, "box_caption": "RiceSpike 0.425", "scores": {"class_score": 0.42529296875}, "domain": "pixel"}, {"position": {"minX": 19.155616760253906, "minY": 297.5047607421875, "maxX": 66.90689086914062, "maxY": 313.9952392578125}, "class_id": 0, "box_caption": "RiceSpike 0.416", "scores": {"class_score": 0.416259765625}, "domain": "pixel"}, {"position": {"minX": 118.15089416503906, "minY": 166.94244384765625, "maxX": 240.34910583496094, "maxY": 201.55755615234375}, "class_id": 0, "box_caption": "RiceSpike 0.406", "scores": {"class_score": 0.405517578125}, "domain": "pixel"}, {"position": {"minX": 16.11862564086914, "minY": 140.64817810058594, "maxX": 133.63137817382812, "maxY": 200.35182189941406}, "class_id": 0, "box_caption": "RiceSpike 0.396", "scores": {"class_score": 0.39599609375}, "domain": "pixel"}, {"position": {"minX": 17.760162353515625, "minY": 500.64239501953125, "maxX": 79.30233764648438, "maxY": 525.3576049804688}, "class_id": 0, "box_caption": "RiceSpike 0.376", "scores": {"class_score": 0.376220703125}, "domain": "pixel"}, {"position": {"minX": 17.6591796875, "minY": 356.015380859375, "maxX": 87.2783203125, "maxY": 408.484619140625}, "class_id": 0, "box_caption": "RiceSpike 0.376", "scores": {"class_score": 0.376220703125}, "domain": "pixel"}, {"position": {"minX": 597.5597534179688, "minY": 235.02183532714844, "maxX": 644.4402465820312, "maxY": 248.97816467285156}, "class_id": 0, "box_caption": "RiceSpike 0.368", "scores": {"class_score": 0.368408203125}, "domain": "pixel"}, {"position": {"minX": 65.36290740966797, "minY": 198.82904052734375, "maxX": 241.6370849609375, "maxY": 272.67095947265625}, "class_id": 0, "box_caption": "RiceSpike 0.358", "scores": {"class_score": 0.3583984375}, "domain": "pixel"}, {"position": {"minX": 416.0816345214844, "minY": 174.8745574951172, "maxX": 459.9183654785156, "maxY": 196.6254425048828}, "class_id": 0, "box_caption": "RiceSpike 0.353", "scores": {"class_score": 0.35302734375}, "domain": "pixel"}, {"position": {"minX": 27.952560424804688, "minY": 309.1497802734375, "maxX": 243.0474395751953, "maxY": 404.8502197265625}, "class_id": 0, "box_caption": "RiceSpike 0.352", "scores": {"class_score": 0.3515625}, "domain": "pixel"}, {"position": {"minX": 15.188648223876953, "minY": 147.48414611816406, "maxX": 123.56135559082031, "maxY": 189.51585388183594}, "class_id": 0, "box_caption": "RiceSpike 0.345", "scores": {"class_score": 0.345458984375}, "domain": "pixel"}, {"position": {"minX": 127.88737487792969, "minY": 166.4858856201172, "maxX": 233.8626251220703, "maxY": 194.0141143798828}, "class_id": 0, "box_caption": "RiceSpike 0.341", "scores": {"class_score": 0.34130859375}, "domain": "pixel"}, {"position": {"minX": 957.6431274414062, "minY": 445.6510925292969, "maxX": 988.3568725585938, "maxY": 487.8489074707031}, "class_id": 0, "box_caption": "RiceSpike 0.341", "scores": {"class_score": 0.3408203125}, "domain": "pixel"}, {"position": {"minX": 595.6822509765625, "minY": 575.4667358398438, "maxX": 622.3177490234375, "maxY": 591.5332641601562}, "class_id": 0, "box_caption": "RiceSpike 0.335", "scores": {"class_score": 0.335205078125}, "domain": "pixel"}, {"position": {"minX": 626.993896484375, "minY": 554.1676635742188, "maxX": 659.006103515625, "maxY": 568.8323364257812}, "class_id": 0, "box_caption": "RiceSpike 0.328", "scores": {"class_score": 0.32763671875}, "domain": "pixel"}, {"position": {"minX": 687.5372314453125, "minY": 574.9176635742188, "maxX": 706.4627685546875, "maxY": 591.0823364257812}, "class_id": 0, "box_caption": "RiceSpike 0.323", "scores": {"class_score": 0.3232421875}, "domain": "pixel"}, {"position": {"minX": 33.84844970703125, "minY": 291.2872314453125, "maxX": 239.15155029296875, "maxY": 430.7127685546875}, "class_id": 0, "box_caption": "RiceSpike 0.313", "scores": {"class_score": 0.313232421875}, "domain": "pixel"}, {"position": {"minX": 689.6246337890625, "minY": 576.4456176757812, "maxX": 704.3753662109375, "maxY": 589.5543823242188}, "class_id": 0, "box_caption": "RiceSpike 0.309", "scores": {"class_score": 0.309326171875}, "domain": "pixel"}, {"position": {"minX": 29.961685180664062, "minY": 367.55645751953125, "maxX": 130.53829956054688, "maxY": 383.94354248046875}, "class_id": 0, "box_caption": "RiceSpike 0.307", "scores": {"class_score": 0.306884765625}, "domain": "pixel"}, {"position": {"minX": 17.49505615234375, "minY": 297.5265808105469, "maxX": 72.12993621826172, "maxY": 317.9734191894531}, "class_id": 0, "box_caption": "RiceSpike 0.301", "scores": {"class_score": 0.30078125}, "domain": "pixel"}, {"position": {"minX": 52.91017150878906, "minY": 325.46893310546875, "maxX": 169.58984375, "maxY": 353.03106689453125}, "class_id": 0, "box_caption": "RiceSpike 0.299", "scores": {"class_score": 0.299072265625}, "domain": "pixel"}, {"position": {"minX": 50.67292785644531, "minY": 293.44952392578125, "maxX": 162.0770721435547, "maxY": 393.55047607421875}, "class_id": 0, "box_caption": "RiceSpike 0.299", "scores": {"class_score": 0.299072265625}, "domain": "pixel"}, {"position": {"minX": 56.28955078125, "minY": 498.98779296875, "maxX": 218.21044921875, "maxY": 513.01220703125}, "class_id": 0, "box_caption": "RiceSpike 0.289", "scores": {"class_score": 0.288818359375}, "domain": "pixel"}, {"position": {"minX": 501.0443115234375, "minY": 263.13055419921875, "maxX": 529.9556884765625, "maxY": 301.36944580078125}, "class_id": 0, "box_caption": "RiceSpike 0.278", "scores": {"class_score": 0.277587890625}, "domain": "pixel"}, {"position": {"minX": 78.32095336914062, "minY": 332.3486633300781, "maxX": 151.92904663085938, "maxY": 344.6513366699219}, "class_id": 0, "box_caption": "RiceSpike 0.276", "scores": {"class_score": 0.275634765625}, "domain": "pixel"}, {"position": {"minX": 295.945068359375, "minY": 569.1221313476562, "maxX": 346.054931640625, "maxY": 582.8778686523438}, "class_id": 0, "box_caption": "RiceSpike 0.272", "scores": {"class_score": 0.2724609375}, "domain": "pixel"}, {"position": {"minX": 44.70458984375, "minY": 322.406494140625, "maxX": 183.79541015625, "maxY": 363.093505859375}, "class_id": 0, "box_caption": "RiceSpike 0.270", "scores": {"class_score": 0.270263671875}, "domain": "pixel"}, {"position": {"minX": 32.25, "minY": 364.75390625, "maxX": 127.5, "maxY": 379.74609375}, "class_id": 0, "box_caption": "RiceSpike 0.266", "scores": {"class_score": 0.265869140625}, "domain": "pixel"}, {"position": {"minX": 12.378463745117188, "minY": 268.647705078125, "maxX": 102.12153625488281, "maxY": 298.352294921875}, "class_id": 0, "box_caption": "RiceSpike 0.265", "scores": {"class_score": 0.2646484375}, "domain": "pixel"}, {"position": {"minX": 300.1955261230469, "minY": 564.6654663085938, "maxX": 343.8044738769531, "maxY": 580.3345336914062}, "class_id": 0, "box_caption": "RiceSpike 0.263", "scores": {"class_score": 0.263427734375}, "domain": "pixel"}, {"position": {"minX": 10.707328796386719, "minY": 148.93788146972656, "maxX": 88.48017120361328, "maxY": 179.31211853027344}, "class_id": 0, "box_caption": "RiceSpike 0.250", "scores": {"class_score": 0.25048828125}, "domain": "pixel"}, {"position": {"minX": 312.1265563964844, "minY": 173.51412963867188, "maxX": 354.8734436035156, "maxY": 199.98587036132812}, "class_id": 0, "box_caption": "RiceSpike 0.248", "scores": {"class_score": 0.2481689453125}, "domain": "pixel"}, {"position": {"minX": 18.808135986328125, "minY": 505.08929443359375, "maxX": 84.50435638427734, "maxY": 524.9107055664062}, "class_id": 0, "box_caption": "RiceSpike 0.244", "scores": {"class_score": 0.2440185546875}, "domain": "pixel"}, {"position": {"minX": 84.8125, "minY": 585.28515625, "maxX": 117.0625, "maxY": 590.71484375}, "class_id": 0, "box_caption": "RiceSpike 0.244", "scores": {"class_score": 0.24365234375}, "domain": "pixel"}, {"position": {"minX": 276.1944580078125, "minY": 583.0198364257812, "maxX": 295.8055419921875, "maxY": 592.9801635742188}, "class_id": 0, "box_caption": "RiceSpike 0.231", "scores": {"class_score": 0.2310791015625}, "domain": "pixel"}, {"position": {"minX": 495.77899169921875, "minY": 262.5703125, "maxX": 533.2210083007812, "maxY": 301.9296875}, "class_id": 0, "box_caption": "RiceSpike 0.223", "scores": {"class_score": 0.2225341796875}, "domain": "pixel"}, {"position": {"minX": 31.27984619140625, "minY": 355.8368835449219, "maxX": 168.22015380859375, "maxY": 379.1631164550781}, "class_id": 0, "box_caption": "RiceSpike 0.222", "scores": {"class_score": 0.22216796875}, "domain": "pixel"}, {"position": {"minX": 412.2484436035156, "minY": 178.14425659179688, "maxX": 469.2515563964844, "maxY": 200.10574340820312}, "class_id": 0, "box_caption": "RiceSpike 0.215", "scores": {"class_score": 0.214599609375}, "domain": "pixel"}, {"position": {"minX": 14.443292617797852, "minY": 298.5337219238281, "maxX": 70.05670166015625, "maxY": 320.9662780761719}, "class_id": 0, "box_caption": "RiceSpike 0.214", "scores": {"class_score": 0.2142333984375}, "domain": "pixel"}, {"position": {"minX": 44.494873046875, "minY": 294.594970703125, "maxX": 168.755126953125, "maxY": 387.905029296875}, "class_id": 0, "box_caption": "RiceSpike 0.214", "scores": {"class_score": 0.213623046875}, "domain": "pixel"}, {"position": {"minX": 54.02763366699219, "minY": 333.325439453125, "maxX": 211.9723663330078, "maxY": 371.674560546875}, "class_id": 0, "box_caption": "RiceSpike 0.209", "scores": {"class_score": 0.2088623046875}, "domain": "pixel"}, {"position": {"minX": 623.9061279296875, "minY": 550.7703857421875, "maxX": 662.0938720703125, "maxY": 570.2296142578125}, "class_id": 0, "box_caption": "RiceSpike 0.208", "scores": {"class_score": 0.20751953125}, "domain": "pixel"}, {"position": {"minX": 162.16751098632812, "minY": 17.842220306396484, "maxX": 271.8324890136719, "maxY": 118.78277587890625}, "class_id": 0, "box_caption": "RiceSpike 0.207", "scores": {"class_score": 0.2066650390625}, "domain": "pixel"}, {"position": {"minX": 413.04449462890625, "minY": 172.4853973388672, "maxX": 466.45550537109375, "maxY": 196.2646026611328}, "class_id": 0, "box_caption": "RiceSpike 0.204", "scores": {"class_score": 0.203857421875}, "domain": "pixel"}, {"position": {"minX": 299.39154052734375, "minY": 565.4392700195312, "maxX": 336.10845947265625, "maxY": 575.5607299804688}, "class_id": 0, "box_caption": "RiceSpike 0.200", "scores": {"class_score": 0.1998291015625}, "domain": "pixel"}, {"position": {"minX": 87.5, "minY": 335.130859375, "maxX": 144.0, "maxY": 341.869140625}, "class_id": 0, "box_caption": "RiceSpike 0.199", "scores": {"class_score": 0.1990966796875}, "domain": "pixel"}, {"position": {"minX": 624.6013793945312, "minY": 554.4215698242188, "maxX": 655.3986206054688, "maxY": 568.5784301757812}, "class_id": 0, "box_caption": "RiceSpike 0.191", "scores": {"class_score": 0.1910400390625}, "domain": "pixel"}, {"position": {"minX": 286.20135498046875, "minY": 313.6863098144531, "maxX": 437.79864501953125, "maxY": 396.8136901855469}, "class_id": 0, "box_caption": "RiceSpike 0.184", "scores": {"class_score": 0.183837890625}, "domain": "pixel"}, {"position": {"minX": 12.29754638671875, "minY": 144.36566162109375, "maxX": 100.32746124267578, "maxY": 181.63433837890625}, "class_id": 0, "box_caption": "RiceSpike 0.183", "scores": {"class_score": 0.182861328125}, "domain": "pixel"}, {"position": {"minX": 96.42591857910156, "minY": 330.48095703125, "maxX": 186.32408142089844, "maxY": 346.01904296875}, "class_id": 0, "box_caption": "RiceSpike 0.173", "scores": {"class_score": 0.173095703125}, "domain": "pixel"}, {"position": {"minX": 14.595245361328125, "minY": 145.06764221191406, "maxX": 84.96725463867188, "maxY": 181.18235778808594}, "class_id": 0, "box_caption": "RiceSpike 0.163", "scores": {"class_score": 0.16259765625}, "domain": "pixel"}, {"position": {"minX": 684.9409790039062, "minY": 577.3108520507812, "maxX": 704.0590209960938, "maxY": 592.6891479492188}, "class_id": 0, "box_caption": "RiceSpike 0.161", "scores": {"class_score": 0.1612548828125}, "domain": "pixel"}, {"position": {"minX": 600.8929443359375, "minY": 230.82806396484375, "maxX": 649.1070556640625, "maxY": 248.67193603515625}, "class_id": 0, "box_caption": "RiceSpike 0.160", "scores": {"class_score": 0.15966796875}, "domain": "pixel"}, {"position": {"minX": 293.8966369628906, "minY": 565.26171875, "maxX": 340.1033630371094, "maxY": 579.73828125}, "class_id": 0, "box_caption": "RiceSpike 0.157", "scores": {"class_score": 0.156982421875}, "domain": "pixel"}, {"position": {"minX": 37.88494873046875, "minY": 296.5202941894531, "maxX": 180.36505126953125, "maxY": 384.4797058105469}, "class_id": 0, "box_caption": "RiceSpike 0.156", "scores": {"class_score": 0.15625}, "domain": "pixel"}, {"position": {"minX": 344.3691711425781, "minY": 147.5640869140625, "maxX": 434.6308288574219, "maxY": 265.1859130859375}, "class_id": 0, "box_caption": "RiceSpike 0.149", "scores": {"class_score": 0.14892578125}, "domain": "pixel"}, {"position": {"minX": 492.148681640625, "minY": 281.3105163574219, "maxX": 513.851318359375, "maxY": 296.6894836425781}, "class_id": 0, "box_caption": "RiceSpike 0.149", "scores": {"class_score": 0.14892578125}, "domain": "pixel"}, {"position": {"minX": 597.9513549804688, "minY": 572.6964721679688, "maxX": 618.0486450195312, "maxY": 591.3035278320312}, "class_id": 0, "box_caption": "RiceSpike 0.146", "scores": {"class_score": 0.14599609375}, "domain": "pixel"}, {"position": {"minX": 495.01806640625, "minY": 281.0654602050781, "maxX": 519.48193359375, "maxY": 300.4345397949219}, "class_id": 0, "box_caption": "RiceSpike 0.144", "scores": {"class_score": 0.14404296875}, "domain": "pixel"}, {"position": {"minX": 503.1580505371094, "minY": 263.7066955566406, "maxX": 533.8419189453125, "maxY": 304.7933044433594}, "class_id": 0, "box_caption": "RiceSpike 0.141", "scores": {"class_score": 0.1407470703125}, "domain": "pixel"}, {"position": {"minX": 21.24842071533203, "minY": 273.3729248046875, "maxX": 99.31407928466797, "maxY": 292.6270751953125}, "class_id": 0, "box_caption": "RiceSpike 0.139", "scores": {"class_score": 0.1387939453125}, "domain": "pixel"}, {"position": {"minX": 689.3389282226562, "minY": 578.4451904296875, "maxX": 707.6610717773438, "maxY": 593.5548095703125}, "class_id": 0, "box_caption": "RiceSpike 0.137", "scores": {"class_score": 0.1370849609375}, "domain": "pixel"}, {"position": {"minX": 500.67236328125, "minY": 265.2969665527344, "maxX": 531.32763671875, "maxY": 296.7030334472656}, "class_id": 0, "box_caption": "RiceSpike 0.124", "scores": {"class_score": 0.1243896484375}, "domain": "pixel"}, {"position": {"minX": 494.13287353515625, "minY": 267.63287353515625, "maxX": 524.8671264648438, "maxY": 298.36712646484375}, "class_id": 0, "box_caption": "RiceSpike 0.123", "scores": {"class_score": 0.12322998046875}, "domain": "pixel"}, {"position": {"minX": 17.83697509765625, "minY": 149.17823791503906, "maxX": 84.47552490234375, "maxY": 183.32176208496094}, "class_id": 0, "box_caption": "RiceSpike 0.122", "scores": {"class_score": 0.12176513671875}, "domain": "pixel"}, {"position": {"minX": 619.3079223632812, "minY": 551.61767578125, "maxX": 661.6920776367188, "maxY": 576.38232421875}, "class_id": 0, "box_caption": "RiceSpike 0.121", "scores": {"class_score": 0.12060546875}, "domain": "pixel"}, {"position": {"minX": 21.709379196166992, "minY": 146.92454528808594, "maxX": 78.91561889648438, "maxY": 178.07545471191406}, "class_id": 0, "box_caption": "RiceSpike 0.117", "scores": {"class_score": 0.1170654296875}, "domain": "pixel"}, {"position": {"minX": 595.855712890625, "minY": 223.204345703125, "maxX": 668.144287109375, "maxY": 265.2956237792969}, "class_id": 0, "box_caption": "RiceSpike 0.112", "scores": {"class_score": 0.11212158203125}, "domain": "pixel"}, {"position": {"minX": 76.50970458984375, "minY": 392.2384338378906, "maxX": 256.24029541015625, "maxY": 449.7615661621094}, "class_id": 0, "box_caption": "RiceSpike 0.105", "scores": {"class_score": 0.10498046875}, "domain": "pixel"}, {"position": {"minX": 288.7785949707031, "minY": 562.4661254882812, "maxX": 347.2214050292969, "maxY": 580.5338745117188}, "class_id": 0, "box_caption": "RiceSpike 0.103", "scores": {"class_score": 0.1029052734375}, "domain": "pixel"}, {"position": {"minX": 52.70965576171875, "minY": 500.3668212890625, "maxX": 211.54034423828125, "maxY": 518.1331787109375}, "class_id": 0, "box_caption": "RiceSpike 0.100", "scores": {"class_score": 0.09991455078125}, "domain": "pixel"}, {"position": {"minX": 498.523193359375, "minY": 261.89892578125, "maxX": 539.476806640625, "maxY": 306.10107421875}, "class_id": 0, "box_caption": "RiceSpike 0.098", "scores": {"class_score": 0.09796142578125}, "domain": "pixel"}, {"position": {"minX": 5.363006591796875, "minY": 142.58486938476562, "maxX": 110.8869857788086, "maxY": 189.91513061523438}, "class_id": 0, "box_caption": "RiceSpike 0.098", "scores": {"class_score": 0.097900390625}, "domain": "pixel"}, {"position": {"minX": 493.08734130859375, "minY": 262.8142395019531, "maxX": 533.9126586914062, "maxY": 304.6857604980469}, "class_id": 0, "box_caption": "RiceSpike 0.096", "scores": {"class_score": 0.09625244140625}, "domain": "pixel"}, {"position": {"minX": 490.324462890625, "minY": 280.143798828125, "maxX": 508.175537109375, "maxY": 291.856201171875}, "class_id": 0, "box_caption": "RiceSpike 0.090", "scores": {"class_score": 0.08966064453125}, "domain": "pixel"}, {"position": {"minX": 279.16485595703125, "minY": 582.2291870117188, "maxX": 302.83514404296875, "maxY": 591.7708129882812}, "class_id": 0, "box_caption": "RiceSpike 0.088", "scores": {"class_score": 0.08795166015625}, "domain": "pixel"}, {"position": {"minX": 5.565223693847656, "minY": 148.0616912841797, "maxX": 111.93477630615234, "maxY": 183.9383087158203}, "class_id": 0, "box_caption": "RiceSpike 0.088", "scores": {"class_score": 0.087890625}, "domain": "pixel"}, {"position": {"minX": 291.8269958496094, "minY": 304.7704772949219, "maxX": 412.6730041503906, "maxY": 397.2295227050781}, "class_id": 0, "box_caption": "RiceSpike 0.087", "scores": {"class_score": 0.08660888671875}, "domain": "pixel"}, {"position": {"minX": 410.8562927246094, "minY": 175.32806396484375, "maxX": 451.1437072753906, "maxY": 191.42193603515625}, "class_id": 0, "box_caption": "RiceSpike 0.085", "scores": {"class_score": 0.0850830078125}, "domain": "pixel"}, {"position": {"minX": 496.739990234375, "minY": 283.27606201171875, "maxX": 520.760009765625, "maxY": 303.72393798828125}, "class_id": 0, "box_caption": "RiceSpike 0.081", "scores": {"class_score": 0.0806884765625}, "domain": "pixel"}, {"position": {"minX": 171.35592651367188, "minY": 367.71014404296875, "maxX": 342.6440734863281, "maxY": 435.28985595703125}, "class_id": 0, "box_caption": "RiceSpike 0.080", "scores": {"class_score": 0.080322265625}, "domain": "pixel"}, {"position": {"minX": 77.63411712646484, "minY": 383.32147216796875, "maxX": 248.86587524414062, "maxY": 458.17852783203125}, "class_id": 0, "box_caption": "RiceSpike 0.077", "scores": {"class_score": 0.077392578125}, "domain": "pixel"}, {"position": {"minX": 50.53858184814453, "minY": 289.7702941894531, "maxX": 241.71142578125, "maxY": 441.7297058105469}, "class_id": 0, "box_caption": "RiceSpike 0.077", "scores": {"class_score": 0.0772705078125}, "domain": "pixel"}, {"position": {"minX": 87.9542465209961, "minY": 583.1376342773438, "maxX": 122.5457534790039, "maxY": 592.8623657226562}, "class_id": 0, "box_caption": "RiceSpike 0.077", "scores": {"class_score": 0.07684326171875}, "domain": "pixel"}, {"position": {"minX": 490.3481140136719, "minY": 278.23291015625, "maxX": 509.1518859863281, "maxY": 291.76708984375}, "class_id": 0, "box_caption": "RiceSpike 0.076", "scores": {"class_score": 0.07635498046875}, "domain": "pixel"}, {"position": {"minX": 688.0431518554688, "minY": 574.6969604492188, "maxX": 700.9568481445312, "maxY": 591.3030395507812}, "class_id": 0, "box_caption": "RiceSpike 0.072", "scores": {"class_score": 0.07183837890625}, "domain": "pixel"}, {"position": {"minX": 599.4412841796875, "minY": 221.20672607421875, "maxX": 674.5587158203125, "maxY": 276.29327392578125}, "class_id": 0, "box_caption": "RiceSpike 0.072", "scores": {"class_score": 0.07177734375}, "domain": "pixel"}, {"position": {"minX": 487.5906677246094, "minY": 276.9496765136719, "maxX": 511.4093322753906, "maxY": 293.5503234863281}, "class_id": 0, "box_caption": "RiceSpike 0.072", "scores": {"class_score": 0.07177734375}, "domain": "pixel"}, {"position": {"minX": 603.7142944335938, "minY": 89.6093521118164, "maxX": 670.2857055664062, "maxY": 177.89065551757812}, "class_id": 0, "box_caption": "RiceSpike 0.071", "scores": {"class_score": 0.0709228515625}, "domain": "pixel"}, {"position": {"minX": 274.4829406738281, "minY": 582.8787841796875, "maxX": 290.5170593261719, "maxY": 590.1212158203125}, "class_id": 0, "box_caption": "RiceSpike 0.068", "scores": {"class_score": 0.068359375}, "domain": "pixel"}, {"position": {"minX": 495.47637939453125, "minY": 271.3430480957031, "maxX": 533.5236206054688, "maxY": 306.6569519042969}, "class_id": 0, "box_caption": "RiceSpike 0.067", "scores": {"class_score": 0.06683349609375}, "domain": "pixel"}, {"position": {"minX": 689.3011474609375, "minY": 573.6539306640625, "maxX": 702.6988525390625, "maxY": 592.3460693359375}, "class_id": 0, "box_caption": "RiceSpike 0.064", "scores": {"class_score": 0.063720703125}, "domain": "pixel"}, {"position": {"minX": 92.82343292236328, "minY": 583.8328857421875, "maxX": 125.42656707763672, "maxY": 591.1671142578125}, "class_id": 0, "box_caption": "RiceSpike 0.063", "scores": {"class_score": 0.0631103515625}, "domain": "pixel"}, {"position": {"minX": 629.453369140625, "minY": 554.7119750976562, "maxX": 663.546630859375, "maxY": 568.2880249023438}, "class_id": 0, "box_caption": "RiceSpike 0.062", "scores": {"class_score": 0.06243896484375}, "domain": "pixel"}, {"position": {"minX": 57.24366760253906, "minY": 364.1113586425781, "maxX": 250.75633239746094, "maxY": 462.3886413574219}, "class_id": 0, "box_caption": "RiceSpike 0.059", "scores": {"class_score": 0.058929443359375}, "domain": "pixel"}, {"position": {"minX": 603.4671020507812, "minY": 231.63661193847656, "maxX": 651.5328979492188, "maxY": 253.86338806152344}, "class_id": 0, "box_caption": "RiceSpike 0.056", "scores": {"class_score": 0.056488037109375}, "domain": "pixel"}, {"position": {"minX": 85.13085174560547, "minY": 585.8795776367188, "maxX": 113.86914825439453, "maxY": 593.1204223632812}, "class_id": 0, "box_caption": "RiceSpike 0.056", "scores": {"class_score": 0.05621337890625}, "domain": "pixel"}, {"position": {"minX": 63.4761962890625, "minY": 313.2529296875, "maxX": 167.6488037109375, "maxY": 369.2470703125}, "class_id": 0, "box_caption": "RiceSpike 0.056", "scores": {"class_score": 0.05615234375}, "domain": "pixel"}, {"position": {"minX": 90.39517211914062, "minY": 339.53411865234375, "maxX": 242.10482788085938, "maxY": 429.96588134765625}, "class_id": 0, "box_caption": "RiceSpike 0.056", "scores": {"class_score": 0.0560302734375}, "domain": "pixel"}, {"position": {"minX": 489.55218505859375, "minY": 277.3424987792969, "maxX": 521.4478149414062, "maxY": 302.6575012207031}, "class_id": 0, "box_caption": "RiceSpike 0.056", "scores": {"class_score": 0.055572509765625}, "domain": "pixel"}, {"position": {"minX": 269.8429260253906, "minY": 581.2171020507812, "maxX": 293.6570739746094, "maxY": 592.7828979492188}, "class_id": 0, "box_caption": "RiceSpike 0.054", "scores": {"class_score": 0.05413818359375}, "domain": "pixel"}, {"position": {"minX": 78.76958465576172, "minY": 583.9990844726562, "maxX": 112.85541534423828, "maxY": 591.0009155273438}, "class_id": 0, "box_caption": "RiceSpike 0.053", "scores": {"class_score": 0.0533447265625}, "domain": "pixel"}, {"position": {"minX": 11.637496948242188, "minY": 296.8868408203125, "maxX": 229.6125030517578, "maxY": 412.6131591796875}, "class_id": 0, "box_caption": "RiceSpike 0.053", "scores": {"class_score": 0.0533447265625}, "domain": "pixel"}, {"position": {"minX": 611.02587890625, "minY": 545.187255859375, "maxX": 664.97412109375, "maxY": 573.812744140625}, "class_id": 0, "box_caption": "RiceSpike 0.053", "scores": {"class_score": 0.053314208984375}, "domain": "pixel"}, {"position": {"minX": 117.08174133300781, "minY": 369.4790344238281, "maxX": 233.1682586669922, "maxY": 411.0209655761719}, "class_id": 0, "box_caption": "RiceSpike 0.053", "scores": {"class_score": 0.052734375}, "domain": "pixel"}, {"position": {"minX": 9.579544067382812, "minY": 354.9420471191406, "maxX": 76.04545593261719, "maxY": 403.5579528808594}, "class_id": 0, "box_caption": "RiceSpike 0.052", "scores": {"class_score": 0.052490234375}, "domain": "pixel"}, {"position": {"minX": 10.964912414550781, "minY": 349.95855712890625, "maxX": 73.72258758544922, "maxY": 397.54144287109375}, "class_id": 0, "box_caption": "RiceSpike 0.052", "scores": {"class_score": 0.052276611328125}, "domain": "pixel"}, {"position": {"minX": 618.6011352539062, "minY": 553.1716918945312, "maxX": 665.3988647460938, "maxY": 572.8283081054688}, "class_id": 0, "box_caption": "RiceSpike 0.052", "scores": {"class_score": 0.051788330078125}, "domain": "pixel"}, {"position": {"minX": 601.1184692382812, "minY": 236.4698486328125, "maxX": 654.8815307617188, "maxY": 257.7801513671875}, "class_id": 0, "box_caption": "RiceSpike 0.051", "scores": {"class_score": 0.05096435546875}, "domain": "pixel"}, {"position": {"minX": 146.85086059570312, "minY": 20.813995361328125, "maxX": 256.6491394042969, "maxY": 110.18600463867188}, "class_id": 0, "box_caption": "RiceSpike 0.050", "scores": {"class_score": 0.0498046875}, "domain": "pixel"}, {"position": {"minX": 103.27740478515625, "minY": 355.0044860839844, "maxX": 239.72259521484375, "maxY": 421.9955139160156}, "class_id": 0, "box_caption": "RiceSpike 0.048", "scores": {"class_score": 0.04827880859375}, "domain": "pixel"}, {"position": {"minX": 124.35028076171875, "minY": 361.0748291015625, "maxX": 307.89971923828125, "maxY": 428.9251708984375}, "class_id": 0, "box_caption": "RiceSpike 0.047", "scores": {"class_score": 0.047271728515625}, "domain": "pixel"}, {"position": {"minX": 130.12171936035156, "minY": 141.42141723632812, "maxX": 146.12828063964844, "maxY": 150.57858276367188}, "class_id": 0, "box_caption": "RiceSpike 0.047", "scores": {"class_score": 0.046600341796875}, "domain": "pixel"}, {"position": {"minX": 485.54022216796875, "minY": 281.1805419921875, "maxX": 505.45977783203125, "maxY": 290.8194580078125}, "class_id": 0, "box_caption": "RiceSpike 0.045", "scores": {"class_score": 0.044769287109375}, "domain": "pixel"}, {"position": {"minX": 347.63348388671875, "minY": 159.3643798828125, "maxX": 452.86651611328125, "maxY": 261.6355895996094}, "class_id": 0, "box_caption": "RiceSpike 0.043", "scores": {"class_score": 0.042999267578125}, "domain": "pixel"}, {"position": {"minX": 413.7974853515625, "minY": 172.9829559326172, "maxX": 459.7025146484375, "maxY": 193.7670440673828}, "class_id": 0, "box_caption": "RiceSpike 0.043", "scores": {"class_score": 0.042938232421875}, "domain": "pixel"}, {"position": {"minX": 321.1910095214844, "minY": 534.0761108398438, "maxX": 437.8089904785156, "maxY": 567.9238891601562}, "class_id": 0, "box_caption": "RiceSpike 0.042", "scores": {"class_score": 0.042388916015625}, "domain": "pixel"}, {"position": {"minX": 15.083137512207031, "minY": 354.8098449707031, "maxX": 101.41686248779297, "maxY": 398.6901550292969}, "class_id": 0, "box_caption": "RiceSpike 0.040", "scores": {"class_score": 0.04010009765625}, "domain": "pixel"}, {"position": {"minX": 59.16014099121094, "minY": 485.9130859375, "maxX": 195.21485900878906, "maxY": 531.5869140625}, "class_id": 0, "box_caption": "RiceSpike 0.040", "scores": {"class_score": 0.039703369140625}, "domain": "pixel"}, {"position": {"minX": 26.07160186767578, "minY": 358.9666442871094, "maxX": 102.42839813232422, "maxY": 403.0333557128906}, "class_id": 0, "box_caption": "RiceSpike 0.039", "scores": {"class_score": 0.038909912109375}, "domain": "pixel"}, {"position": {"minX": 9.246574401855469, "minY": 266.751953125, "maxX": 104.50342559814453, "maxY": 312.248046875}, "class_id": 0, "box_caption": "RiceSpike 0.038", "scores": {"class_score": 0.03753662109375}, "domain": "pixel"}, {"position": {"minX": 951.2042236328125, "minY": 441.9954833984375, "maxX": 989.7957763671875, "maxY": 484.0045166015625}, "class_id": 0, "box_caption": "RiceSpike 0.036", "scores": {"class_score": 0.035888671875}, "domain": "pixel"}, {"position": {"minX": 117.47245788574219, "minY": 169.51736450195312, "maxX": 223.0275421142578, "maxY": 188.23263549804688}, "class_id": 0, "box_caption": "RiceSpike 0.035", "scores": {"class_score": 0.03497314453125}, "domain": "pixel"}, {"position": {"minX": 612.9583740234375, "minY": 550.4429931640625, "maxX": 664.0416259765625, "maxY": 580.5570068359375}, "class_id": 0, "box_caption": "RiceSpike 0.034", "scores": {"class_score": 0.034332275390625}, "domain": "pixel"}, {"position": {"minX": 17.477935791015625, "minY": 150.11767578125, "maxX": 132.39706420898438, "maxY": 206.88232421875}, "class_id": 0, "box_caption": "RiceSpike 0.033", "scores": {"class_score": 0.033477783203125}, "domain": "pixel"}, {"position": {"minX": 10.222671508789062, "minY": 362.39373779296875, "maxX": 95.90232849121094, "maxY": 387.10626220703125}, "class_id": 0, "box_caption": "RiceSpike 0.033", "scores": {"class_score": 0.03302001953125}, "domain": "pixel"}, {"position": {"minX": 486.4368896484375, "minY": 278.7145080566406, "maxX": 504.5631103515625, "maxY": 292.2854919433594}, "class_id": 0, "box_caption": "RiceSpike 0.032", "scores": {"class_score": 0.0322265625}, "domain": "pixel"}, {"position": {"minX": 28.186790466308594, "minY": 158.02847290039062, "maxX": 126.6882095336914, "maxY": 197.72152709960938}, "class_id": 0, "box_caption": "RiceSpike 0.031", "scores": {"class_score": 0.0309906005859375}, "domain": "pixel"}, {"position": {"minX": 9.99774169921875, "minY": 354.5780334472656, "maxX": 93.25225830078125, "maxY": 394.4219665527344}, "class_id": 0, "box_caption": "RiceSpike 0.031", "scores": {"class_score": 0.0309600830078125}, "domain": "pixel"}, {"position": {"minX": 59.183746337890625, "minY": 324.6685485839844, "maxX": 154.56625366210938, "maxY": 352.8314514160156}, "class_id": 0, "box_caption": "RiceSpike 0.031", "scores": {"class_score": 0.0308837890625}, "domain": "pixel"}, {"position": {"minX": 78.24148559570312, "minY": 587.8412475585938, "maxX": 123.50851440429688, "maxY": 597.1587524414062}, "class_id": 0, "box_caption": "RiceSpike 0.030", "scores": {"class_score": 0.0299530029296875}, "domain": "pixel"}, {"position": {"minX": 502.73468017578125, "minY": 262.4389343261719, "maxX": 528.2653198242188, "maxY": 295.0610656738281}, "class_id": 0, "box_caption": "RiceSpike 0.030", "scores": {"class_score": 0.02972412109375}, "domain": "pixel"}, {"position": {"minX": 277.0938720703125, "minY": 585.4151000976562, "maxX": 300.4061279296875, "maxY": 592.5848999023438}, "class_id": 0, "box_caption": "RiceSpike 0.028", "scores": {"class_score": 0.028045654296875}, "domain": "pixel"}, {"position": {"minX": 315.0528259277344, "minY": 167.53318786621094, "maxX": 370.4471740722656, "maxY": 205.71681213378906}, "class_id": 0, "box_caption": "RiceSpike 0.028", "scores": {"class_score": 0.02777099609375}, "domain": "pixel"}, {"position": {"minX": 272.5496520996094, "minY": 565.9745483398438, "maxX": 345.9503479003906, "maxY": 591.0254516601562}, "class_id": 0, "box_caption": "RiceSpike 0.026", "scores": {"class_score": 0.0261077880859375}, "domain": "pixel"}, {"position": {"minX": 27.660778045654297, "minY": 360.75885009765625, "maxX": 102.58921813964844, "maxY": 409.24114990234375}, "class_id": 0, "box_caption": "RiceSpike 0.025", "scores": {"class_score": 0.025146484375}, "domain": "pixel"}, {"position": {"minX": 60.31092834472656, "minY": 194.096923828125, "maxX": 205.43907165527344, "maxY": 261.903076171875}, "class_id": 0, "box_caption": "RiceSpike 0.025", "scores": {"class_score": 0.0246734619140625}, "domain": "pixel"}, {"position": {"minX": 949.816162109375, "minY": 443.395751953125, "maxX": 981.183837890625, "maxY": 481.604248046875}, "class_id": 0, "box_caption": "RiceSpike 0.023", "scores": {"class_score": 0.023345947265625}, "domain": "pixel"}, {"position": {"minX": 413.4072265625, "minY": 176.20523071289062, "maxX": 437.0927734375, "maxY": 187.79476928710938}, "class_id": 0, "box_caption": "RiceSpike 0.022", "scores": {"class_score": 0.02239990234375}, "domain": "pixel"}, {"position": {"minX": 32.9486083984375, "minY": 289.49237060546875, "maxX": 177.67640686035156, "maxY": 405.00762939453125}, "class_id": 0, "box_caption": "RiceSpike 0.022", "scores": {"class_score": 0.02203369140625}, "domain": "pixel"}, {"position": {"minX": 51.2124137878418, "minY": 280.98089599609375, "maxX": 158.91258239746094, "maxY": 412.51910400390625}, "class_id": 0, "box_caption": "RiceSpike 0.022", "scores": {"class_score": 0.0217742919921875}, "domain": "pixel"}, {"position": {"minX": 604.4259643554688, "minY": 577.8341674804688, "maxX": 627.5740356445312, "maxY": 591.1658325195312}, "class_id": 0, "box_caption": "RiceSpike 0.021", "scores": {"class_score": 0.0212860107421875}, "domain": "pixel"}, {"position": {"minX": 17.0, "minY": 277.26953125, "maxX": 94.75, "maxY": 288.23046875}, "class_id": 0, "box_caption": "RiceSpike 0.021", "scores": {"class_score": 0.0205535888671875}, "domain": "pixel"}, {"position": {"minX": 273.3164367675781, "minY": 572.428466796875, "maxX": 343.1835632324219, "maxY": 595.571533203125}, "class_id": 0, "box_caption": "RiceSpike 0.020", "scores": {"class_score": 0.020477294921875}, "domain": "pixel"}, {"position": {"minX": 35.97523498535156, "minY": 288.619873046875, "maxX": 164.39976501464844, "maxY": 406.880126953125}, "class_id": 0, "box_caption": "RiceSpike 0.020", "scores": {"class_score": 0.0203857421875}, "domain": "pixel"}, {"position": {"minX": 417.553466796875, "minY": 177.0411834716797, "maxX": 474.946533203125, "maxY": 198.2088165283203}, "class_id": 0, "box_caption": "RiceSpike 0.020", "scores": {"class_score": 0.020233154296875}, "domain": "pixel"}, {"position": {"minX": 291.4553527832031, "minY": 566.0388793945312, "maxX": 327.5446472167969, "maxY": 575.9611206054688}, "class_id": 0, "box_caption": "RiceSpike 0.020", "scores": {"class_score": 0.0200347900390625}, "domain": "pixel"}, {"position": {"minX": 26.04296112060547, "minY": 359.7423400878906, "maxX": 116.20703887939453, "maxY": 382.2576599121094}, "class_id": 0, "box_caption": "RiceSpike 0.020", "scores": {"class_score": 0.0199432373046875}, "domain": "pixel"}, {"position": {"minX": 630.732666015625, "minY": 548.1576538085938, "maxX": 663.267333984375, "maxY": 565.8423461914062}, "class_id": 0, "box_caption": "RiceSpike 0.018", "scores": {"class_score": 0.018402099609375}, "domain": "pixel"}, {"position": {"minX": 84.06172180175781, "minY": 585.6954345703125, "maxX": 128.0632781982422, "maxY": 592.3045654296875}, "class_id": 0, "box_caption": "RiceSpike 0.018", "scores": {"class_score": 0.0179443359375}, "domain": "pixel"}, {"position": {"minX": 499.29644775390625, "minY": 281.71099853515625, "maxX": 527.7035522460938, "maxY": 308.78900146484375}, "class_id": 0, "box_caption": "RiceSpike 0.018", "scores": {"class_score": 0.0179290771484375}, "domain": "pixel"}, {"position": {"minX": 98.37345123291016, "minY": 60.526329040527344, "maxX": 123.75154876708984, "maxY": 94.34867095947266}, "class_id": 0, "box_caption": "RiceSpike 0.017", "scores": {"class_score": 0.016876220703125}, "domain": "pixel"}, {"position": {"minX": 323.734130859375, "minY": 527.9977416992188, "maxX": 449.265869140625, "maxY": 573.0022583007812}, "class_id": 0, "box_caption": "RiceSpike 0.017", "scores": {"class_score": 0.016632080078125}, "domain": "pixel"}, {"position": {"minX": 142.24127197265625, "minY": 376.16217041015625, "maxX": 286.25872802734375, "maxY": 421.83782958984375}, "class_id": 0, "box_caption": "RiceSpike 0.016", "scores": {"class_score": 0.01593017578125}, "domain": "pixel"}, {"position": {"minX": 163.76824951171875, "minY": 23.261985778808594, "maxX": 265.98175048828125, "maxY": 122.4880142211914}, "class_id": 0, "box_caption": "RiceSpike 0.015", "scores": {"class_score": 0.01507568359375}, "domain": "pixel"}, {"position": {"minX": 487.36297607421875, "minY": 273.14501953125, "maxX": 532.1370239257812, "maxY": 308.35498046875}, "class_id": 0, "box_caption": "RiceSpike 0.015", "scores": {"class_score": 0.01502227783203125}, "domain": "pixel"}, {"position": {"minX": 335.8377990722656, "minY": 526.9476928710938, "maxX": 437.6622009277344, "maxY": 574.0523071289062}, "class_id": 0, "box_caption": "RiceSpike 0.015", "scores": {"class_score": 0.014862060546875}, "domain": "pixel"}, {"position": {"minX": 32.25816345214844, "minY": 139.48583984375, "maxX": 129.11683654785156, "maxY": 197.76416015625}, "class_id": 0, "box_caption": "RiceSpike 0.015", "scores": {"class_score": 0.01451873779296875}, "domain": "pixel"}, {"position": {"minX": 497.3182373046875, "minY": 282.4930725097656, "maxX": 530.6817626953125, "maxY": 307.0069274902344}, "class_id": 0, "box_caption": "RiceSpike 0.014", "scores": {"class_score": 0.0143280029296875}, "domain": "pixel"}, {"position": {"minX": 595.5040283203125, "minY": 571.9174194335938, "maxX": 612.4959716796875, "maxY": 586.0825805664062}, "class_id": 0, "box_caption": "RiceSpike 0.014", "scores": {"class_score": 0.0143280029296875}, "domain": "pixel"}, {"position": {"minX": 595.3612670898438, "minY": 88.90303039550781, "maxX": 668.6387329101562, "maxY": 179.3469696044922}, "class_id": 0, "box_caption": "RiceSpike 0.014", "scores": {"class_score": 0.01392364501953125}, "domain": "pixel"}, {"position": {"minX": 450.63360595703125, "minY": 477.84417724609375, "maxX": 486.86639404296875, "maxY": 493.65582275390625}, "class_id": 0, "box_caption": "RiceSpike 0.014", "scores": {"class_score": 0.013824462890625}, "domain": "pixel"}, {"position": {"minX": 40.81024169921875, "minY": 287.9387512207031, "maxX": 149.43975830078125, "maxY": 388.0612487792969}, "class_id": 0, "box_caption": "RiceSpike 0.014", "scores": {"class_score": 0.0135345458984375}, "domain": "pixel"}, {"position": {"minX": 95.27499389648438, "minY": 61.32329559326172, "maxX": 126.35000610351562, "maxY": 95.17670440673828}, "class_id": 0, "box_caption": "RiceSpike 0.013", "scores": {"class_score": 0.01348876953125}, "domain": "pixel"}, {"position": {"minX": 329.4127502441406, "minY": 539.414306640625, "maxX": 445.5872497558594, "maxY": 573.585693359375}, "class_id": 0, "box_caption": "RiceSpike 0.013", "scores": {"class_score": 0.01343536376953125}, "domain": "pixel"}, {"position": {"minX": 139.1727294921875, "minY": 370.4568786621094, "maxX": 296.3272705078125, "maxY": 426.5431213378906}, "class_id": 0, "box_caption": "RiceSpike 0.013", "scores": {"class_score": 0.01328277587890625}, "domain": "pixel"}, {"position": {"minX": 650.1419677734375, "minY": 44.487762451171875, "maxX": 681.8580322265625, "maxY": 85.76223754882812}, "class_id": 0, "box_caption": "RiceSpike 0.013", "scores": {"class_score": 0.013214111328125}, "domain": "pixel"}, {"position": {"minX": 693.1301879882812, "minY": 580.2657470703125, "maxX": 711.8698120117188, "maxY": 590.7342529296875}, "class_id": 0, "box_caption": "RiceSpike 0.013", "scores": {"class_score": 0.01316070556640625}, "domain": "pixel"}, {"position": {"minX": 499.31878662109375, "minY": 262.7301025390625, "maxX": 540.6812133789062, "maxY": 315.2698974609375}, "class_id": 0, "box_caption": "RiceSpike 0.013", "scores": {"class_score": 0.013092041015625}, "domain": "pixel"}, {"position": {"minX": 165.57467651367188, "minY": 23.68475341796875, "maxX": 264.9253234863281, "maxY": 103.19024658203125}, "class_id": 0, "box_caption": "RiceSpike 0.013", "scores": {"class_score": 0.01261138916015625}, "domain": "pixel"}, {"position": {"minX": 131.487548828125, "minY": 141.29849243164062, "maxX": 152.512451171875, "maxY": 151.45150756835938}, "class_id": 0, "box_caption": "RiceSpike 0.012", "scores": {"class_score": 0.01174163818359375}, "domain": "pixel"}, {"position": {"minX": 340.1077880859375, "minY": 166.619384765625, "maxX": 456.8922119140625, "maxY": 259.880615234375}, "class_id": 0, "box_caption": "RiceSpike 0.011", "scores": {"class_score": 0.0114898681640625}, "domain": "pixel"}, {"position": {"minX": 313.4283752441406, "minY": 165.88592529296875, "maxX": 346.0716247558594, "maxY": 195.11407470703125}, "class_id": 0, "box_caption": "RiceSpike 0.011", "scores": {"class_score": 0.010986328125}, "domain": "pixel"}, {"position": {"minX": 11.181320190429688, "minY": 355.4012145996094, "maxX": 114.44367218017578, "maxY": 411.0987854003906}, "class_id": 0, "box_caption": "RiceSpike 0.011", "scores": {"class_score": 0.010986328125}, "domain": "pixel"}, {"position": {"minX": 19.24651336669922, "minY": 274.01812744140625, "maxX": 78.37849426269531, "maxY": 294.48187255859375}, "class_id": 0, "box_caption": "RiceSpike 0.011", "scores": {"class_score": 0.0108184814453125}, "domain": "pixel"}, {"position": {"minX": 597.421630859375, "minY": 571.0662231445312, "maxX": 614.578369140625, "maxY": 587.9337768554688}, "class_id": 0, "box_caption": "RiceSpike 0.011", "scores": {"class_score": 0.01050567626953125}, "domain": "pixel"}, {"position": {"minX": 119.9031982421875, "minY": 363.96624755859375, "maxX": 276.8468017578125, "maxY": 425.03375244140625}, "class_id": 0, "box_caption": "RiceSpike 0.010", "scores": {"class_score": 0.010345458984375}, "domain": "pixel"}, {"position": {"minX": 19.37454605102539, "minY": 506.78631591796875, "maxX": 55.18795394897461, "maxY": 521.2136840820312}, "class_id": 0, "box_caption": "RiceSpike 0.010", "scores": {"class_score": 0.01026153564453125}, "domain": "pixel"}, {"position": {"minX": 297.9493103027344, "minY": 568.8768920898438, "maxX": 361.0506896972656, "maxY": 578.1231079101562}, "class_id": 0, "box_caption": "RiceSpike 0.010", "scores": {"class_score": 0.01009368896484375}, "domain": "pixel"}], "class_labels": {"0": "RiceSpike", "1": "none"}}